HWDesign2016/FullAdderStructure.v
module FullAdderStructure ( x, y, cin, cout, s );
  input x, y, cin;
  output cout, s;
  wire w1, w2, w3, w4, w5;

  and a1 ( w1, x, y );
  and a2 ( w2, y, cin );
  and a3 ( w3, cin, x );
  or o1 ( w4, w1, w2 );
  or o2 ( cout, w4, w3 );
  xor x1 ( w5, x, y );
  xor x2 ( s, w5, cin );
endmodule

HWDesign2016/simFullAdderStructure.v
module simFullAdderStructure;
wire	cout, s ;
reg		x, y, cin;
reg		ck;
initial begin
$monitor( "%t %b + %b + %b = %b%b", $time, cin, x, y, cout, s);
$dumpfile("simFullAdderStructure.vcd");
$dumpvars;
x <= 0;
y <= 0;
cin <= 0;
ck <= 0;
end
always  #10 ck <= ~ck;
always @(negedge ck) begin
if( {cin,x,y} == 7 ) begin
$finish;
end
end
always @(posedge ck) begin
{cin, x, y} <= {cin, x, y} + 1;
end
FullAdderStructure FAS ( x, y, cin, cout, s );
endmodule

//hwdesign2016@vdec.u-tokyo.ac.jp
//subject HWdesign20160415

HWDesign2016/simFullAdderFunction.vcd
$date
	Fri Apr 15 14:05:25 2016
$end
$version
	Icarus Verilog
$end
$timescale
	1s
$end
$scope module simFullAdderStructure $end
$var wire 1 ! cout $end
$var wire 1 " s $end
$var reg 1 # cin $end
$var reg 1 $ ck $end
$var reg 1 % x $end
$var reg 1 & y $end
$scope module FAS $end
$var wire 1 ' cin $end
$var wire 1 ! cout $end
$var wire 1 " s $end
$var wire 1 ( w1 $end
$var wire 1 ) w2 $end
$var wire 1 * w3 $end
$var wire 1 + w4 $end
$var wire 1 , w5 $end
$var wire 1 - x $end
$var wire 1 . y $end
$upscope $end
$upscope $end
$enddefinitions $end
#0
$dumpvars
0.
0-
0,
0+
0*
0)
0(
0'
0&
0%
0$
0#
0"
0!
$end
#10
1"
1,
1&
1.
1$
#20
0$
#30
1%
1-
0&
0.
1$
#40
0$
#50
1!
1+
0"
1(
0,
1&
1.
1$
#60
0$
#70
0!
0+
1"
0(
1#
1'
0%
0-
0&
0.
1$
#80
0$
#90
1!
1+
0"
1)
1,
1&
1.
1$
#100
0$
#110
0+
1*
0)
1%
1-
0&
0.
1$
#120
0$
#130
1+
1"
1(
1)
0,
1&
1.
1$
