ComputerArchitecture/cpu.v
module fetch (pc, ins);
   input [31:0] pc;
   output [31:0] ins;
   reg [31:0]    ins_mem[0:255];
   initial
      $readmemb("sample.bnr", ins_mem);
   assign ins = ins_mem[pc];
endmodule

module execute (clk, ins, pc, reg1, reg2, wra, result, nextpc);
   input clk;
   input [31:0] ins, pc, reg1, reg2;
   output [4:0] wra;
   output [31:0] result, nextpc;
   wire [5:0]    op;
   wire [4:0]    shift, operation;
   wire [25:0]   addr;
   wire [31:0]   dpl_imm, operand2, alu_result, nonbranch, branch, mem_address, dm_r_data;
   wire [3:0]    wren;

   function [4:0] opr_gen;
      input [5:0] op;
      input [4:0] operation;
      case (op)
        6'd0: opr_gen = operation;
        6'd1: opr_gen = 5'd0;
        6'd4: opr_gen = 5'd8;
        6'd5: opr_gen = 5'd9;
        6'd6: opr_gen = 5'd10;
        default: opr_gen = 5'h1f;
      endcase
   endfunction

   function [31:0] alu;
      input [4:0] opr, shift;
      input [31:0] operand1, operand2;
      case (opr)
        5'd0: alu = operand1 + operand2;
        5'd1: alu = operand1 - operand2;
        5'd8: alu = operand1 & operand2;
        5'd9: alu = operand1 | operand2;
        5'd10: alu = operand1 ^ operand2;
        5'd11: alu = ~ (operand1 & operand2);
        5'd16: alu = operand1 << shift;
        5'd17: alu = operand1 >> shift;
        5'd18: alu = operand1 >>> shift;
        default: alu = 32'hffffffff;
      endcase
   endfunction

   function [31:0] calc;
      input [5:0]  op;
      input [31:0] alu_result, dpl_imm, dm_r_data, pc;
      case (op)
        6'd0, 6'd1, 6'd4, 6'd5, 6'd6: calc = alu_result;
        6'd3: calc = dpl_imm << 16;
        6'd16: calc = dm_r_data;
        6'd18: calc = {{16{dm_r_data[15]}}, dm_r_data[15:0]};
        6'd20: calc = {{24{dm_r_data[7]}}, dm_r_data[7:0]};
        6'd41: calc = pc+32'd1;
        default: calc = 32'hffffffff;
      endcase
   endfunction

   function [31:0] npc;
      input [5:0]  op;
      input [31:0] reg1, reg2, branch, nonbranch, addr;
      case (op)
        6'd32: npc = (reg1 == reg2)? branch : nonbranch;
        6'd33: npc = (reg1 != reg2)? branch : nonbranch;
        6'd34: npc = (reg1 < reg2)? branch : nonbranch;
        6'd35: npc = (reg1 <= reg2)? branch : nonbranch;
        6'd40, 6'd41: npc = addr;
        6'd42: npc = reg1;
        default: npc = nonbranch;
      endcase
   endfunction

   function [4:0] wreg;
      input [5:0]  op;
      input [4:0]  rt, rd;
      case (op)
        6'd0: wreg = rd;
        6'd1, 6'd3, 6'd4, 6'd5, 6'd6, 6'd16, 6'd18, 6'd20: wreg = rt;
        6'd41: wreg = 5'd31;
        default: wreg = 5'd0;
      endcase
   endfunction

   function [3:0] wrengen;
      input [5:0]  op;
      case (op)
        6'd24: wrengen = 4'b0000;
        6'd26: wrengen = 4'b1100;
        6'd28: wrengen = 4'b1110;
        default: wrengen = 4'b1111;
      endcase
   endfunction

   assign op = ins [31:26] ;
   assign shift = ins [10:6] ;
   assign operation = ins [4:0] ;
   assign dpl_imm = {{16{ins[15]}} , ins [15:0]};
   assign operand2 = (op == 6'd0) ? reg2: dpl_imm;
   assign alu_result = alu (opr_gen (op, operation) , shift, reg1, operand2);
   assign mem_address = reg1 + dpl_imm >>> 2;
   assign wren = wrengen(op);
   data_mem data_mem_body0(mem_address[7:0], clk, reg2[7:0], wren[0], dm_r_data [7:0]);
   data_mem data_mem_body1(mem_address[7:0], clk, reg2[15:8], wren[1], dm_r_data[15:8]);
   data_mem data_mem_body2(mem_address[7:0], clk, reg2[23:16], wren[2], dm_r_data[23:16]);
   data_mem data_mem_body3(mem_address[7:0], clk, reg2[31:24], wren[3], dm_r_data[31:24]);
   assign wra = wreg(op, ins[20:16], ins[15:11]);
   assign result = calc (op, alu_result, dpl_imm, dm_r_data, pc);
   assign addr = ins[25:0];
   assign nonbranch = pc+32'd1; assign branch = nonbranch + dpl_imm;
   assign nextpc = npc(op, reg1, reg2, branch, nonbranch, addr);
endmodule

module data_mem(address, clk, write_data, wren, read_data);
   input [7:0] address;
   input       clk, wren;
   input [7:0] write_data;
   output [7:0] read_data;
   reg [7:0]    d_mem [0:255] ;

   always @(posedge clk)
     if (wren == 0) d_mem[address] <= write_data;
   assign read_data = d_mem[address];
endmodule

module writeback(clk, rstd, nextpc, pc);
   input clk, rstd;
   input [31:0] nextpc;
   output [31:0] pc;
   reg [31:0] pc;
   always @(negedge rstd or posedge clk)
     begin
        if (rstd == 0) pc <= 32'h00000000;
        else if (clk == 1) pc <= nextpc;
     end
endmodule

module reg_file(clk, rstd, wr, ra1, ra2, wa, wren, rr1, rr2);
   input clk, rstd, wren;
   input [31:0] wr;
   input [4:0]  ra1, ra2, wa;
   output [31:0] rr1, rr2;
   reg [31:0]    rf [0:31];
   assign rr1 = rf[ra1];
   assign rr2 = rf[ra2];
   always @(negedge rstd or posedge clk) begin
     if (rstd == 0) rf [0] <= 32'h00000000;
     else if (wren == 0) rf[wa] <= wr;
   end
endmodule

module computer(clk, rstd);
   input clk, rstd;
   wire [31:0] pc, ins, reg1,reg2, result, nextpc;
   wire [4:0]  wra;
   wire [3:0]  wren;
   fetch fetch_body (pc[7:0], ins);
   execute execute_body (clk, ins, pc, reg1, reg2, wra, result, nextpc);
   writeback writeback_body (clk, rstd, nextpc, pc);
   reg_file rf_body (clk, rstd, result, ins[25:21], ins[20:16], wra, (~| wra) , reg1, reg2);
endmodule

module tcomputer;
   reg clk, rstd;

   initial begin
      rstd = 1;
      #10 rstd = 0;
      #20 rstd = 1;
      #10000 $finish;
   end

   initial begin
      clk = 0;
      $dumpfile("cpu.vcd");
      $dumpvars;
   end

   always #50 clk=~clk;

   computer computer_body(clk, rstd);

endmodule

ComputerArchitecture/cpu.vcd
$date
	Thu Jun 30 21:28:39 2016
$end
$version
	Icarus Verilog
$end
$timescale
	1s
$end
$scope module tcomputer $end
$var reg 1 ! clk $end
$var reg 1 " rstd $end
$scope module computer_body $end
$var wire 1 # clk $end
$var wire 32 $ ins [31:0] $end
$var wire 32 % nextpc [31:0] $end
$var wire 32 & pc [31:0] $end
$var wire 32 ' reg1 [31:0] $end
$var wire 32 ( reg2 [31:0] $end
$var wire 32 ) result [31:0] $end
$var wire 1 * rstd $end
$var wire 5 + wra [4:0] $end
$scope module fetch_body $end
$var wire 32 , ins [31:0] $end
$var wire 32 - pc [31:0] $end
$upscope $end
$scope module execute_body $end
$var wire 26 . addr [25:0] $end
$var wire 32 / alu_result [31:0] $end
$var wire 32 0 branch [31:0] $end
$var wire 1 # clk $end
$var wire 32 1 dm_r_data [31:0] $end
$var wire 32 2 dpl_imm [31:0] $end
$var wire 32 3 ins [31:0] $end
$var wire 32 4 mem_address [31:0] $end
$var wire 32 5 nextpc [31:0] $end
$var wire 32 6 nonbranch [31:0] $end
$var wire 6 7 op [5:0] $end
$var wire 32 8 operand2 [31:0] $end
$var wire 5 9 operation [4:0] $end
$var wire 32 : pc [31:0] $end
$var wire 32 ; reg1 [31:0] $end
$var wire 32 < reg2 [31:0] $end
$var wire 32 = result [31:0] $end
$var wire 5 > shift [4:0] $end
$var wire 5 ? wra [4:0] $end
$var wire 4 @ wren [3:0] $end
$scope function alu $end
$var reg 32 A alu [31:0] $end
$var reg 32 B operand1 [31:0] $end
$var reg 32 C operand2 [31:0] $end
$var reg 5 D opr [4:0] $end
$var reg 5 E shift [4:0] $end
$upscope $end
$scope function calc $end
$var reg 32 F alu_result [31:0] $end
$var reg 32 G calc [31:0] $end
$var reg 32 H dm_r_data [31:0] $end
$var reg 32 I dpl_imm [31:0] $end
$var reg 6 J op [5:0] $end
$var reg 32 K pc [31:0] $end
$upscope $end
$scope function npc $end
$var reg 32 L addr [31:0] $end
$var reg 32 M branch [31:0] $end
$var reg 32 N nonbranch [31:0] $end
$var reg 32 O npc [31:0] $end
$var reg 6 P op [5:0] $end
$var reg 32 Q reg1 [31:0] $end
$var reg 32 R reg2 [31:0] $end
$upscope $end
$scope function opr_gen $end
$var reg 6 S op [5:0] $end
$var reg 5 T operation [4:0] $end
$var reg 5 U opr_gen [4:0] $end
$upscope $end
$scope function wreg $end
$var reg 6 V op [5:0] $end
$var reg 5 W rd [4:0] $end
$var reg 5 X rt [4:0] $end
$var reg 5 Y wreg [4:0] $end
$upscope $end
$scope function wrengen $end
$var reg 6 Z op [5:0] $end
$var reg 4 [ wrengen [3:0] $end
$upscope $end
$scope module data_mem_body0 $end
$var wire 8 \ address [7:0] $end
$var wire 1 # clk $end
$var wire 8 ] read_data [7:0] $end
$var wire 1 ^ wren $end
$var wire 8 _ write_data [7:0] $end
$upscope $end
$scope module data_mem_body1 $end
$var wire 8 ` address [7:0] $end
$var wire 1 # clk $end
$var wire 8 a read_data [7:0] $end
$var wire 1 b wren $end
$var wire 8 c write_data [7:0] $end
$upscope $end
$scope module data_mem_body2 $end
$var wire 8 d address [7:0] $end
$var wire 1 # clk $end
$var wire 8 e read_data [7:0] $end
$var wire 1 f wren $end
$var wire 8 g write_data [7:0] $end
$upscope $end
$scope module data_mem_body3 $end
$var wire 8 h address [7:0] $end
$var wire 1 # clk $end
$var wire 8 i read_data [7:0] $end
$var wire 1 j wren $end
$var wire 8 k write_data [7:0] $end
$upscope $end
$upscope $end
$scope module writeback_body $end
$var wire 1 # clk $end
$var wire 32 l nextpc [31:0] $end
$var wire 1 * rstd $end
$var reg 32 m pc [31:0] $end
$upscope $end
$scope module rf_body $end
$var wire 1 # clk $end
$var wire 5 n ra1 [4:0] $end
$var wire 5 o ra2 [4:0] $end
$var wire 32 p rr1 [31:0] $end
$var wire 32 q rr2 [31:0] $end
$var wire 1 * rstd $end
$var wire 5 r wa [4:0] $end
$var wire 32 s wr [31:0] $end
$var wire 1 t wren $end
$upscope $end
$upscope $end
$upscope $end
$enddefinitions $end
#0
$dumpvars
1t
b11111111111111111111111111111111 s
b0 r
bx q
bx p
bx o
bx n
bx m
bx l
bx k
1j
bx i
bx h
bx g
1f
bx e
bx d
bx c
1b
bx a
bx `
bx _
1^
bx ]
bx \
b1111 [
bx Z
b0 Y
bx X
bx W
bx V
b11111 U
bx T
bx S
bx R
bx Q
bx P
bx O
bx N
bx M
b0xxxxxxxxxxxxxxxxxxxxxxxxxx L
bx K
bx J
bx I
bx H
b11111111111111111111111111111111 G
b11111111111111111111111111111111 F
bx E
b11111 D
bx C
bx B
b11111111111111111111111111111111 A
b1111 @
b0 ?
bx >
b11111111111111111111111111111111 =
bx <
bx ;
bx :
bx 9
bx 8
bx 7
bx 6
bx 5
b0xxxxxxxxxxxxxxxxxxxxxxxxxxxxxx 4
bx 3
bx 2
bx 1
bx 0
b11111111111111111111111111111111 /
bx .
b0xxxxxxxx -
bx ,
b0 +
1*
b11111111111111111111111111111111 )
bx (
bx '
bx &
bx %
bx $
0#
1"
0!
$end
#10
b1 )
b1 =
b1 s
b1 G
b1 F
b0 \
b0 `
b0 d
b0 h
b1 /
b1 A
b1 C
b0 D
b1 Z
b0 U
b1 T
b1 S
b0 4
b1 8
b1 I
b1 J
0t
b1 +
b1 ?
b1 r
b1 Y
b0 W
b1 X
b1 V
b10000000000000001 L
b10 M
b0 Q
b1 P
b0 B
b0 E
b1 7
b0 >
b1 9
b10 0
b1 2
b10000000000000001 .
b1 o
b0 n
b0 '
b0 ;
b0 p
b1 %
b1 5
b1 l
b1 O
b1 N
b0 K
b0 -
b100000000010000000000000001 $
b100000000010000000000000001 ,
b100000000010000000000000001 3
b0 m
b1 6
b0 &
b0 :
0"
0*
#30
1"
1*
#50
b10 )
b10 =
b10 s
b10 G
b10 F
b10 +
b10 ?
b10 r
b10 Y
b10 X
b1000100000000000000001 L
b1 Q
b10 /
b10 A
b1 B
b1000100000000000000001 .
b10 o
b1 n
b1 '
b1 ;
b1 p
bx k
bx g
bx c
bx _
b10 %
b10 5
b10 l
b10 O
b10 N
b11 M
bx R
b1 K
b1 -
b100001000100000000000000001 $
b100001000100000000000000001 ,
b100001000100000000000000001 3
bx (
bx <
bx q
b1 m
b11 0
b10 6
b1 &
b1 :
1!
1#
#100
0!
0#
#150
bx C
b11111 D
bx \
bx `
bx d
bx h
bx Z
b11111 U
bx T
bx S
bx 8
b11111111111111111111111111111111 )
b11111111111111111111111111111111 =
b11111111111111111111111111111111 s
b11111111111111111111111111111111 G
bx I
b11111111111111111111111111111111 F
bx J
1t
b0 +
b0 ?
b0 r
b0 Y
bx W
bx X
bx V
b0xxxxxxxxxxxxxxxxxxxxxxxxxx L
bx Q
bx P
b0xxxxxxxxxxxxxxxxxxxxxxxxxxxxxx 4
b11111111111111111111111111111111 /
b11111111111111111111111111111111 A
bx B
bx E
bx 7
bx >
bx 9
bx 2
bx .
bx o
bx n
bx '
bx ;
bx p
b10 K
b10 -
bx $
bx ,
bx 3
b11 %
b11 5
b11 l
b11 O
b11 N
bx M
bx R
bx k
bx g
bx c
bx _
b10 m
bx 0
b11 6
b10 &
b10 :
bx (
bx <
bx q
1!
1#
#200
0!
0#
#250
b100 %
b100 5
b100 l
b100 O
b100 N
b11 K
b11 -
b11 m
b100 6
b11 &
b11 :
1!
1#
#300
0!
0#
#350
b101 %
b101 5
b101 l
b101 O
b101 N
b100 K
b100 -
b100 m
b101 6
b100 &
b100 :
1!
1#
#400
0!
0#
#450
b110 %
b110 5
b110 l
b110 O
b110 N
b101 K
b101 -
b101 m
b110 6
b101 &
b101 :
1!
1#
#500
0!
0#
#550
b111 %
b111 5
b111 l
b111 O
b111 N
b110 K
b110 -
b110 m
b111 6
b110 &
b110 :
1!
1#
#600
0!
0#
#650
b1000 %
b1000 5
b1000 l
b1000 O
b1000 N
b111 K
b111 -
b111 m
b1000 6
b111 &
b111 :
1!
1#
#700
0!
0#
#750
b1001 %
b1001 5
b1001 l
b1001 O
b1001 N
b1000 K
b1000 -
b1000 m
b1001 6
b1000 &
b1000 :
1!
1#
#800
0!
0#
#850
b1010 %
b1010 5
b1010 l
b1010 O
b1010 N
b1001 K
b1001 -
b1001 m
b1010 6
b1001 &
b1001 :
1!
1#
#900
0!
0#
#950
b1011 %
b1011 5
b1011 l
b1011 O
b1011 N
b1010 K
b1010 -
b1010 m
b1011 6
b1010 &
b1010 :
1!
1#
#1000
0!
0#
#1050
b1100 %
b1100 5
b1100 l
b1100 O
b1100 N
b1011 K
b1011 -
b1011 m
b1100 6
b1011 &
b1011 :
1!
1#
#1100
0!
0#
#1150
b1101 %
b1101 5
b1101 l
b1101 O
b1101 N
b1100 K
b1100 -
b1100 m
b1101 6
b1100 &
b1100 :
1!
1#
#1200
0!
0#
#1250
b1110 %
b1110 5
b1110 l
b1110 O
b1110 N
b1101 K
b1101 -
b1101 m
b1110 6
b1101 &
b1101 :
1!
1#
#1300
0!
0#
#1350
b1111 %
b1111 5
b1111 l
b1111 O
b1111 N
b1110 K
b1110 -
b1110 m
b1111 6
b1110 &
b1110 :
1!
1#
#1400
0!
0#
#1450
b10000 %
b10000 5
b10000 l
b10000 O
b10000 N
b1111 K
b1111 -
b1111 m
b10000 6
b1111 &
b1111 :
1!
1#
#1500
0!
0#
#1550
b10001 %
b10001 5
b10001 l
b10001 O
b10001 N
b10000 K
b10000 -
b10000 m
b10001 6
b10000 &
b10000 :
1!
1#
#1600
0!
0#
#1650
b10010 %
b10010 5
b10010 l
b10010 O
b10010 N
b10001 K
b10001 -
b10001 m
b10010 6
b10001 &
b10001 :
1!
1#
#1700
0!
0#
#1750
b10011 %
b10011 5
b10011 l
b10011 O
b10011 N
b10010 K
b10010 -
b10010 m
b10011 6
b10010 &
b10010 :
1!
1#
#1800
0!
0#
#1850
b10100 %
b10100 5
b10100 l
b10100 O
b10100 N
b10011 K
b10011 -
b10011 m
b10100 6
b10011 &
b10011 :
1!
1#
#1900
0!
0#
#1950
b10101 %
b10101 5
b10101 l
b10101 O
b10101 N
b10100 K
b10100 -
b10100 m
b10101 6
b10100 &
b10100 :
1!
1#
#2000
0!
0#
#2050
b10110 %
b10110 5
b10110 l
b10110 O
b10110 N
b10101 K
b10101 -
b10101 m
b10110 6
b10101 &
b10101 :
1!
1#
#2100
0!
0#
#2150
b10111 %
b10111 5
b10111 l
b10111 O
b10111 N
b10110 K
b10110 -
b10110 m
b10111 6
b10110 &
b10110 :
1!
1#
#2200
0!
0#
#2250
b11000 %
b11000 5
b11000 l
b11000 O
b11000 N
b10111 K
b10111 -
b10111 m
b11000 6
b10111 &
b10111 :
1!
1#
#2300
0!
0#
#2350
b11001 %
b11001 5
b11001 l
b11001 O
b11001 N
b11000 K
b11000 -
b11000 m
b11001 6
b11000 &
b11000 :
1!
1#
#2400
0!
0#
#2450
b11010 %
b11010 5
b11010 l
b11010 O
b11010 N
b11001 K
b11001 -
b11001 m
b11010 6
b11001 &
b11001 :
1!
1#
#2500
0!
0#
#2550
b11011 %
b11011 5
b11011 l
b11011 O
b11011 N
b11010 K
b11010 -
b11010 m
b11011 6
b11010 &
b11010 :
1!
1#
#2600
0!
0#
#2650
b11100 %
b11100 5
b11100 l
b11100 O
b11100 N
b11011 K
b11011 -
b11011 m
b11100 6
b11011 &
b11011 :
1!
1#
#2700
0!
0#
#2750
b11101 %
b11101 5
b11101 l
b11101 O
b11101 N
b11100 K
b11100 -
b11100 m
b11101 6
b11100 &
b11100 :
1!
1#
#2800
0!
0#
#2850
b11110 %
b11110 5
b11110 l
b11110 O
b11110 N
b11101 K
b11101 -
b11101 m
b11110 6
b11101 &
b11101 :
1!
1#
#2900
0!
0#
#2950
b11111 %
b11111 5
b11111 l
b11111 O
b11111 N
b11110 K
b11110 -
b11110 m
b11111 6
b11110 &
b11110 :
1!
1#
#3000
0!
0#
#3050
b100000 %
b100000 5
b100000 l
b100000 O
b100000 N
b11111 K
b11111 -
b11111 m
b100000 6
b11111 &
b11111 :
1!
1#
#3100
0!
0#
#3150
b100001 %
b100001 5
b100001 l
b100001 O
b100001 N
b100000 K
b100000 -
b100000 m
b100001 6
b100000 &
b100000 :
1!
1#
#3200
0!
0#
#3250
b100010 %
b100010 5
b100010 l
b100010 O
b100010 N
b100001 K
b100001 -
b100001 m
b100010 6
b100001 &
b100001 :
1!
1#
#3300
0!
0#
#3350
b100011 %
b100011 5
b100011 l
b100011 O
b100011 N
b100010 K
b100010 -
b100010 m
b100011 6
b100010 &
b100010 :
1!
1#
#3400
0!
0#
#3450
b100100 %
b100100 5
b100100 l
b100100 O
b100100 N
b100011 K
b100011 -
b100011 m
b100100 6
b100011 &
b100011 :
1!
1#
#3500
0!
0#
#3550
b100101 %
b100101 5
b100101 l
b100101 O
b100101 N
b100100 K
b100100 -
b100100 m
b100101 6
b100100 &
b100100 :
1!
1#
#3600
0!
0#
#3650
b100110 %
b100110 5
b100110 l
b100110 O
b100110 N
b100101 K
b100101 -
b100101 m
b100110 6
b100101 &
b100101 :
1!
1#
#3700
0!
0#
#3750
b100111 %
b100111 5
b100111 l
b100111 O
b100111 N
b100110 K
b100110 -
b100110 m
b100111 6
b100110 &
b100110 :
1!
1#
#3800
0!
0#
#3850
b101000 %
b101000 5
b101000 l
b101000 O
b101000 N
b100111 K
b100111 -
b100111 m
b101000 6
b100111 &
b100111 :
1!
1#
#3900
0!
0#
#3950
b101001 %
b101001 5
b101001 l
b101001 O
b101001 N
b101000 K
b101000 -
b101000 m
b101001 6
b101000 &
b101000 :
1!
1#
#4000
0!
0#
#4050
b101010 %
b101010 5
b101010 l
b101010 O
b101010 N
b101001 K
b101001 -
b101001 m
b101010 6
b101001 &
b101001 :
1!
1#
#4100
0!
0#
#4150
b101011 %
b101011 5
b101011 l
b101011 O
b101011 N
b101010 K
b101010 -
b101010 m
b101011 6
b101010 &
b101010 :
1!
1#
#4200
0!
0#
#4250
b101100 %
b101100 5
b101100 l
b101100 O
b101100 N
b101011 K
b101011 -
b101011 m
b101100 6
b101011 &
b101011 :
1!
1#
#4300
0!
0#
#4350
b101101 %
b101101 5
b101101 l
b101101 O
b101101 N
b101100 K
b101100 -
b101100 m
b101101 6
b101100 &
b101100 :
1!
1#
#4400
0!
0#
#4450
b101110 %
b101110 5
b101110 l
b101110 O
b101110 N
b101101 K
b101101 -
b101101 m
b101110 6
b101101 &
b101101 :
1!
1#
#4500
0!
0#
#4550
b101111 %
b101111 5
b101111 l
b101111 O
b101111 N
b101110 K
b101110 -
b101110 m
b101111 6
b101110 &
b101110 :
1!
1#
#4600
0!
0#
#4650
b110000 %
b110000 5
b110000 l
b110000 O
b110000 N
b101111 K
b101111 -
b101111 m
b110000 6
b101111 &
b101111 :
1!
1#
#4700
0!
0#
#4750
b110001 %
b110001 5
b110001 l
b110001 O
b110001 N
b110000 K
b110000 -
b110000 m
b110001 6
b110000 &
b110000 :
1!
1#
#4800
0!
0#
#4850
b110010 %
b110010 5
b110010 l
b110010 O
b110010 N
b110001 K
b110001 -
b110001 m
b110010 6
b110001 &
b110001 :
1!
1#
#4900
0!
0#
#4950
b110011 %
b110011 5
b110011 l
b110011 O
b110011 N
b110010 K
b110010 -
b110010 m
b110011 6
b110010 &
b110010 :
1!
1#
#5000
0!
0#
#5050
b110100 %
b110100 5
b110100 l
b110100 O
b110100 N
b110011 K
b110011 -
b110011 m
b110100 6
b110011 &
b110011 :
1!
1#
#5100
0!
0#
#5150
b110101 %
b110101 5
b110101 l
b110101 O
b110101 N
b110100 K
b110100 -
b110100 m
b110101 6
b110100 &
b110100 :
1!
1#
#5200
0!
0#
#5250
b110110 %
b110110 5
b110110 l
b110110 O
b110110 N
b110101 K
b110101 -
b110101 m
b110110 6
b110101 &
b110101 :
1!
1#
#5300
0!
0#
#5350
b110111 %
b110111 5
b110111 l
b110111 O
b110111 N
b110110 K
b110110 -
b110110 m
b110111 6
b110110 &
b110110 :
1!
1#
#5400
0!
0#
#5450
b111000 %
b111000 5
b111000 l
b111000 O
b111000 N
b110111 K
b110111 -
b110111 m
b111000 6
b110111 &
b110111 :
1!
1#
#5500
0!
0#
#5550
b111001 %
b111001 5
b111001 l
b111001 O
b111001 N
b111000 K
b111000 -
b111000 m
b111001 6
b111000 &
b111000 :
1!
1#
#5600
0!
0#
#5650
b111010 %
b111010 5
b111010 l
b111010 O
b111010 N
b111001 K
b111001 -
b111001 m
b111010 6
b111001 &
b111001 :
1!
1#
#5700
0!
0#
#5750
b111011 %
b111011 5
b111011 l
b111011 O
b111011 N
b111010 K
b111010 -
b111010 m
b111011 6
b111010 &
b111010 :
1!
1#
#5800
0!
0#
#5850
b111100 %
b111100 5
b111100 l
b111100 O
b111100 N
b111011 K
b111011 -
b111011 m
b111100 6
b111011 &
b111011 :
1!
1#
#5900
0!
0#
#5950
b111101 %
b111101 5
b111101 l
b111101 O
b111101 N
b111100 K
b111100 -
b111100 m
b111101 6
b111100 &
b111100 :
1!
1#
#6000
0!
0#
#6050
b111110 %
b111110 5
b111110 l
b111110 O
b111110 N
b111101 K
b111101 -
b111101 m
b111110 6
b111101 &
b111101 :
1!
1#
#6100
0!
0#
#6150
b111111 %
b111111 5
b111111 l
b111111 O
b111111 N
b111110 K
b111110 -
b111110 m
b111111 6
b111110 &
b111110 :
1!
1#
#6200
0!
0#
#6250
b1000000 %
b1000000 5
b1000000 l
b1000000 O
b1000000 N
b111111 K
b111111 -
b111111 m
b1000000 6
b111111 &
b111111 :
1!
1#
#6300
0!
0#
#6350
b1000001 %
b1000001 5
b1000001 l
b1000001 O
b1000001 N
b1000000 K
b1000000 -
b1000000 m
b1000001 6
b1000000 &
b1000000 :
1!
1#
#6400
0!
0#
#6450
b1000010 %
b1000010 5
b1000010 l
b1000010 O
b1000010 N
b1000001 K
b1000001 -
b1000001 m
b1000010 6
b1000001 &
b1000001 :
1!
1#
#6500
0!
0#
#6550
b1000011 %
b1000011 5
b1000011 l
b1000011 O
b1000011 N
b1000010 K
b1000010 -
b1000010 m
b1000011 6
b1000010 &
b1000010 :
1!
1#
#6600
0!
0#
#6650
b1000100 %
b1000100 5
b1000100 l
b1000100 O
b1000100 N
b1000011 K
b1000011 -
b1000011 m
b1000100 6
b1000011 &
b1000011 :
1!
1#
#6700
0!
0#
#6750
b1000101 %
b1000101 5
b1000101 l
b1000101 O
b1000101 N
b1000100 K
b1000100 -
b1000100 m
b1000101 6
b1000100 &
b1000100 :
1!
1#
#6800
0!
0#
#6850
b1000110 %
b1000110 5
b1000110 l
b1000110 O
b1000110 N
b1000101 K
b1000101 -
b1000101 m
b1000110 6
b1000101 &
b1000101 :
1!
1#
#6900
0!
0#
#6950
b1000111 %
b1000111 5
b1000111 l
b1000111 O
b1000111 N
b1000110 K
b1000110 -
b1000110 m
b1000111 6
b1000110 &
b1000110 :
1!
1#
#7000
0!
0#
#7050
b1001000 %
b1001000 5
b1001000 l
b1001000 O
b1001000 N
b1000111 K
b1000111 -
b1000111 m
b1001000 6
b1000111 &
b1000111 :
1!
1#
#7100
0!
0#
#7150
b1001001 %
b1001001 5
b1001001 l
b1001001 O
b1001001 N
b1001000 K
b1001000 -
b1001000 m
b1001001 6
b1001000 &
b1001000 :
1!
1#
#7200
0!
0#
#7250
b1001010 %
b1001010 5
b1001010 l
b1001010 O
b1001010 N
b1001001 K
b1001001 -
b1001001 m
b1001010 6
b1001001 &
b1001001 :
1!
1#
#7300
0!
0#
#7350
b1001011 %
b1001011 5
b1001011 l
b1001011 O
b1001011 N
b1001010 K
b1001010 -
b1001010 m
b1001011 6
b1001010 &
b1001010 :
1!
1#
#7400
0!
0#
#7450
b1001100 %
b1001100 5
b1001100 l
b1001100 O
b1001100 N
b1001011 K
b1001011 -
b1001011 m
b1001100 6
b1001011 &
b1001011 :
1!
1#
#7500
0!
0#
#7550
b1001101 %
b1001101 5
b1001101 l
b1001101 O
b1001101 N
b1001100 K
b1001100 -
b1001100 m
b1001101 6
b1001100 &
b1001100 :
1!
1#
#7600
0!
0#
#7650
b1001110 %
b1001110 5
b1001110 l
b1001110 O
b1001110 N
b1001101 K
b1001101 -
b1001101 m
b1001110 6
b1001101 &
b1001101 :
1!
1#
#7700
0!
0#
#7750
b1001111 %
b1001111 5
b1001111 l
b1001111 O
b1001111 N
b1001110 K
b1001110 -
b1001110 m
b1001111 6
b1001110 &
b1001110 :
1!
1#
#7800
0!
0#
#7850
b1010000 %
b1010000 5
b1010000 l
b1010000 O
b1010000 N
b1001111 K
b1001111 -
b1001111 m
b1010000 6
b1001111 &
b1001111 :
1!
1#
#7900
0!
0#
#7950
b1010001 %
b1010001 5
b1010001 l
b1010001 O
b1010001 N
b1010000 K
b1010000 -
b1010000 m
b1010001 6
b1010000 &
b1010000 :
1!
1#
#8000
0!
0#
#8050
b1010010 %
b1010010 5
b1010010 l
b1010010 O
b1010010 N
b1010001 K
b1010001 -
b1010001 m
b1010010 6
b1010001 &
b1010001 :
1!
1#
#8100
0!
0#
#8150
b1010011 %
b1010011 5
b1010011 l
b1010011 O
b1010011 N
b1010010 K
b1010010 -
b1010010 m
b1010011 6
b1010010 &
b1010010 :
1!
1#
#8200
0!
0#
#8250
b1010100 %
b1010100 5
b1010100 l
b1010100 O
b1010100 N
b1010011 K
b1010011 -
b1010011 m
b1010100 6
b1010011 &
b1010011 :
1!
1#
#8300
0!
0#
#8350
b1010101 %
b1010101 5
b1010101 l
b1010101 O
b1010101 N
b1010100 K
b1010100 -
b1010100 m
b1010101 6
b1010100 &
b1010100 :
1!
1#
#8400
0!
0#
#8450
b1010110 %
b1010110 5
b1010110 l
b1010110 O
b1010110 N
b1010101 K
b1010101 -
b1010101 m
b1010110 6
b1010101 &
b1010101 :
1!
1#
#8500
0!
0#
#8550
b1010111 %
b1010111 5
b1010111 l
b1010111 O
b1010111 N
b1010110 K
b1010110 -
b1010110 m
b1010111 6
b1010110 &
b1010110 :
1!
1#
#8600
0!
0#
#8650
b1011000 %
b1011000 5
b1011000 l
b1011000 O
b1011000 N
b1010111 K
b1010111 -
b1010111 m
b1011000 6
b1010111 &
b1010111 :
1!
1#
#8700
0!
0#
#8750
b1011001 %
b1011001 5
b1011001 l
b1011001 O
b1011001 N
b1011000 K
b1011000 -
b1011000 m
b1011001 6
b1011000 &
b1011000 :
1!
1#
#8800
0!
0#
#8850
b1011010 %
b1011010 5
b1011010 l
b1011010 O
b1011010 N
b1011001 K
b1011001 -
b1011001 m
b1011010 6
b1011001 &
b1011001 :
1!
1#
#8900
0!
0#
#8950
b1011011 %
b1011011 5
b1011011 l
b1011011 O
b1011011 N
b1011010 K
b1011010 -
b1011010 m
b1011011 6
b1011010 &
b1011010 :
1!
1#
#9000
0!
0#
#9050
b1011100 %
b1011100 5
b1011100 l
b1011100 O
b1011100 N
b1011011 K
b1011011 -
b1011011 m
b1011100 6
b1011011 &
b1011011 :
1!
1#
#9100
0!
0#
#9150
b1011101 %
b1011101 5
b1011101 l
b1011101 O
b1011101 N
b1011100 K
b1011100 -
b1011100 m
b1011101 6
b1011100 &
b1011100 :
1!
1#
#9200
0!
0#
#9250
b1011110 %
b1011110 5
b1011110 l
b1011110 O
b1011110 N
b1011101 K
b1011101 -
b1011101 m
b1011110 6
b1011101 &
b1011101 :
1!
1#
#9300
0!
0#
#9350
b1011111 %
b1011111 5
b1011111 l
b1011111 O
b1011111 N
b1011110 K
b1011110 -
b1011110 m
b1011111 6
b1011110 &
b1011110 :
1!
1#
#9400
0!
0#
#9450
b1100000 %
b1100000 5
b1100000 l
b1100000 O
b1100000 N
b1011111 K
b1011111 -
b1011111 m
b1100000 6
b1011111 &
b1011111 :
1!
1#
#9500
0!
0#
#9550
b1100001 %
b1100001 5
b1100001 l
b1100001 O
b1100001 N
b1100000 K
b1100000 -
b1100000 m
b1100001 6
b1100000 &
b1100000 :
1!
1#
#9600
0!
0#
