ComputerArchitecture/cpu_addBGS.v
module fetch (pc, ins);
   input [31:0] pc;
   output [31:0] ins;
   reg [31:0]    ins_mem[0:255];
   initial
      $readmemb("sample.bnr", ins_mem);
   assign ins = ins_mem[pc];
endmodule

module execute (clk, ins, pc, reg1, reg2, wra, result, nextpc);
   input clk;
   input [31:0] ins, pc, reg1, reg2;
   output [4:0] wra;
   output [31:0] result, nextpc;
   wire [5:0]    op;
   wire [4:0]    shift, operation;
   wire [25:0]   addr;
   wire [31:0]   dpl_imm, operand2, alu_result, nonbranch, branch, mem_address, dm_r_data;
   wire [3:0]    wren;

   function [4:0] opr_gen;
      input [5:0] op;
      input [4:0] operation;
      case (op)
        6'd0: opr_gen = operation;
        6'd1: opr_gen = 5'd0;
        6'd4: opr_gen = 5'd8;
        6'd5: opr_gen = 5'd9;
        6'd6: opr_gen = 5'd10;
        6'd36:opr_gen = 5'd20; //add
        default: opr_gen = 5'h1f;
      endcase
   endfunction

   function [31:0] alu;
      input [4:0] opr, shift;
      input [31:0] operand1, operand2;
      case (opr)
        5'd0: alu = operand1 + operand2;
        5'd2: alu = operand1 - operand2;
        5'd8: alu = operand1 & operand2;
        5'd9: alu = operand1 | operand2;
        5'd10: alu = operand1 ^ operand2;
        5'd11: alu = ~ (operand1 & operand2);
        5'd16: alu = operand1 << shift;
        5'd17: alu = operand1 >> shift;
        5'd18: alu = operand1 >>> shift;
        5'd20: alu = operand2 - operand1; //追加
        default: alu = 32'hffffffff;
      endcase
   endfunction

   function [31:0] calc;
      input [5:0]  op;
      input [31:0] alu_result, dpl_imm, dm_r_data, pc;
      case (op)
        6'd0, 6'd1, 6'd4, 6'd5, 6'd6, 6'd36: calc = alu_result; //変更
        6'd3: calc = dpl_imm << 16;
        6'd16: calc = dm_r_data;
        6'd18: calc = {{16{dm_r_data[15]}}, dm_r_data[15:0]};
        6'd20: calc = {{24{dm_r_data[7]}}, dm_r_data[7:0]};
        6'd41: calc = pc+32'd1;
        default: calc = 32'hffffffff;
      endcase
   endfunction

   function [31:0] npc;
      input [5:0]  op;
      input [31:0] reg1, reg2, branch, nonbranch, addr;
      case (op)
        6'd32: npc = (reg1 == reg2)? branch : nonbranch;
        6'd33: npc = (reg1 != reg2)? branch : nonbranch;
        6'd34, 6'd36: npc = (reg1 < reg2)? branch : nonbranch; //変更
        6'd35: npc = (reg1 <= reg2)? branch : nonbranch;
        6'd40, 6'd41: npc = addr;
        6'd42: npc = reg1;
        default: npc = nonbranch;
      endcase
   endfunction

   function [4:0] wreg;
      input [5:0]  op;
      input [4:0]  rt, rd;
      case (op)
        6'd0: wreg = rd;
        6'd1, 6'd3, 6'd4, 6'd5, 6'd6, 6'd16, 6'd18, 6'd20, 6'd36: wreg = rt; //変更
        6'd41: wreg = 5'd31;
        default: wreg = 5'd0;
      endcase
   endfunction

   function [3:0] wrengen;
      input [5:0]  op;
      case (op)
        6'd24: wrengen = 4'b0000;
        6'd26: wrengen = 4'b1100;
        6'd28: wrengen = 4'b1110;
        default: wrengen = 4'b1111;
      endcase
   endfunction

   assign op = ins [31:26] ;
   assign shift = ins [10:6] ;
   assign operation = ins [4:0] ;
   assign dpl_imm = {{16{ins[15]}} , ins [15:0]};
   assign operand2 = (op == 6'd0 || op == 6'd36) ? reg2: dpl_imm; //変更
   assign alu_result = alu (opr_gen (op, operation) , shift, reg1, operand2);
   assign mem_address = reg1 + dpl_imm >>> 2;
   assign wren = wrengen(op);
   data_mem data_mem_body0(mem_address[7:0], clk, reg2[7:0], wren[0], dm_r_data [7:0]);
   data_mem data_mem_body1(mem_address[7:0], clk, reg2[15:8], wren[1], dm_r_data[15:8]);
   data_mem data_mem_body2(mem_address[7:0], clk, reg2[23:16], wren[2], dm_r_data[23:16]);
   data_mem data_mem_body3(mem_address[7:0], clk, reg2[31:24], wren[3], dm_r_data[31:24]);
   assign wra = wreg(op, ins[20:16], ins[15:11]);
   assign result = calc (op, alu_result, dpl_imm, dm_r_data, pc);
   assign addr = ins[25:0];
   assign nonbranch = pc + 32'd1;
   assign branch = nonbranch + dpl_imm;
   assign nextpc = npc(op, reg1, reg2, branch, nonbranch, addr);
endmodule

module data_mem(address, clk, write_data, wren, read_data);
   input [7:0] address;
   input       clk, wren;
   input [7:0] write_data;
   output [7:0] read_data;
   reg [7:0]    d_mem [0:255] ;

   always @(posedge clk)
     if (wren == 0) d_mem[address] <= write_data;
   assign read_data = d_mem[address];
endmodule

module writeback(clk, rstd, nextpc, pc);
   input clk, rstd;
   input [31:0] nextpc;
   output [31:0] pc;
   reg [31:0] pc;
   always @(negedge rstd or posedge clk)
     begin
        if (rstd == 0) pc <= 32'h00000000;
        else if (clk == 1) pc <= nextpc;
     end
endmodule

module reg_file(clk, rstd, wr, ra1, ra2, wa, wren, rr1, rr2);
   input clk, rstd, wren;
   input [31:0] wr;
   input [4:0]  ra1, ra2, wa;
   output [31:0] rr1, rr2;
   reg [31:0]    rf [0:31];
   assign rr1 = rf[ra1];
   assign rr2 = rf[ra2];
   always @(negedge rstd or posedge clk) begin
     if (rstd == 0) rf [0] <= 32'h00000000;
     else if (wren == 0) rf[wa] <= wr;
   end
endmodule

module computer(clk, rstd);
   input clk, rstd;
   wire [31:0] pc, ins, reg1,reg2, result, nextpc;
   wire [4:0]  wra;
   wire [3:0]  wren;
   fetch fetch_body (pc[7:0], ins);
   execute execute_body (clk, ins, pc, reg1, reg2, wra, result, nextpc);
   writeback writeback_body (clk, rstd, nextpc, pc);
   reg_file rf_body (clk, rstd, result, ins[25:21], ins[20:16], wra, (~| wra) , reg1, reg2);
endmodule

module tcomputer;
   reg clk, rstd;

   initial begin
      rstd = 1;
      #10 rstd = 0;
      #20 rstd = 1;
      #10000 $finish;
   end

   initial begin
      clk = 0;
      $dumpfile("cpu.vcd");
      $dumpvars;
   end

   always #50 clk=~clk;

   computer computer_body(clk, rstd);

endmodule

ComputerArchitecture/cpu.vcd
$date
	Tue Jul  5 22:46:09 2016
$end
$version
	Icarus Verilog
$end
$timescale
	1s
$end
$scope module tcomputer $end
$var reg 1 ! clk $end
$var reg 1 " rstd $end
$scope module computer_body $end
$var wire 1 # clk $end
$var wire 32 $ ins [31:0] $end
$var wire 32 % nextpc [31:0] $end
$var wire 32 & pc [31:0] $end
$var wire 32 ' reg1 [31:0] $end
$var wire 32 ( reg2 [31:0] $end
$var wire 32 ) result [31:0] $end
$var wire 1 * rstd $end
$var wire 5 + wra [4:0] $end
$scope module fetch_body $end
$var wire 32 , ins [31:0] $end
$var wire 32 - pc [31:0] $end
$upscope $end
$scope module execute_body $end
$var wire 26 . addr [25:0] $end
$var wire 32 / alu_result [31:0] $end
$var wire 32 0 branch [31:0] $end
$var wire 1 # clk $end
$var wire 32 1 dm_r_data [31:0] $end
$var wire 32 2 dpl_imm [31:0] $end
$var wire 32 3 ins [31:0] $end
$var wire 32 4 mem_address [31:0] $end
$var wire 32 5 nextpc [31:0] $end
$var wire 32 6 nonbranch [31:0] $end
$var wire 6 7 op [5:0] $end
$var wire 32 8 operand2 [31:0] $end
$var wire 5 9 operation [4:0] $end
$var wire 32 : pc [31:0] $end
$var wire 32 ; reg1 [31:0] $end
$var wire 32 < reg2 [31:0] $end
$var wire 32 = result [31:0] $end
$var wire 5 > shift [4:0] $end
$var wire 5 ? wra [4:0] $end
$var wire 4 @ wren [3:0] $end
$scope function alu $end
$var reg 32 A alu [31:0] $end
$var reg 32 B operand1 [31:0] $end
$var reg 32 C operand2 [31:0] $end
$var reg 5 D opr [4:0] $end
$var reg 5 E shift [4:0] $end
$upscope $end
$scope function calc $end
$var reg 32 F alu_result [31:0] $end
$var reg 32 G calc [31:0] $end
$var reg 32 H dm_r_data [31:0] $end
$var reg 32 I dpl_imm [31:0] $end
$var reg 6 J op [5:0] $end
$var reg 32 K pc [31:0] $end
$upscope $end
$scope function npc $end
$var reg 32 L addr [31:0] $end
$var reg 32 M branch [31:0] $end
$var reg 32 N nonbranch [31:0] $end
$var reg 32 O npc [31:0] $end
$var reg 6 P op [5:0] $end
$var reg 32 Q reg1 [31:0] $end
$var reg 32 R reg2 [31:0] $end
$upscope $end
$scope function opr_gen $end
$var reg 6 S op [5:0] $end
$var reg 5 T operation [4:0] $end
$var reg 5 U opr_gen [4:0] $end
$upscope $end
$scope function wreg $end
$var reg 6 V op [5:0] $end
$var reg 5 W rd [4:0] $end
$var reg 5 X rt [4:0] $end
$var reg 5 Y wreg [4:0] $end
$upscope $end
$scope function wrengen $end
$var reg 6 Z op [5:0] $end
$var reg 4 [ wrengen [3:0] $end
$upscope $end
$scope module data_mem_body0 $end
$var wire 8 \ address [7:0] $end
$var wire 1 # clk $end
$var wire 8 ] read_data [7:0] $end
$var wire 1 ^ wren $end
$var wire 8 _ write_data [7:0] $end
$upscope $end
$scope module data_mem_body1 $end
$var wire 8 ` address [7:0] $end
$var wire 1 # clk $end
$var wire 8 a read_data [7:0] $end
$var wire 1 b wren $end
$var wire 8 c write_data [7:0] $end
$upscope $end
$scope module data_mem_body2 $end
$var wire 8 d address [7:0] $end
$var wire 1 # clk $end
$var wire 8 e read_data [7:0] $end
$var wire 1 f wren $end
$var wire 8 g write_data [7:0] $end
$upscope $end
$scope module data_mem_body3 $end
$var wire 8 h address [7:0] $end
$var wire 1 # clk $end
$var wire 8 i read_data [7:0] $end
$var wire 1 j wren $end
$var wire 8 k write_data [7:0] $end
$upscope $end
$upscope $end
$scope module writeback_body $end
$var wire 1 # clk $end
$var wire 32 l nextpc [31:0] $end
$var wire 1 * rstd $end
$var reg 32 m pc [31:0] $end
$upscope $end
$scope module rf_body $end
$var wire 1 # clk $end
$var wire 5 n ra1 [4:0] $end
$var wire 5 o ra2 [4:0] $end
$var wire 32 p rr1 [31:0] $end
$var wire 32 q rr2 [31:0] $end
$var wire 1 * rstd $end
$var wire 5 r wa [4:0] $end
$var wire 32 s wr [31:0] $end
$var wire 1 t wren $end
$upscope $end
$upscope $end
$upscope $end
$enddefinitions $end
#0
$dumpvars
1t
b11111111111111111111111111111111 s
b0 r
bx q
bx p
bx o
bx n
bx m
bx l
bx k
1j
bx i
bx h
bx g
1f
bx e
bx d
bx c
1b
bx a
bx `
bx _
1^
bx ]
bx \
b1111 [
bx Z
b0 Y
bx X
bx W
bx V
b11111 U
bx T
bx S
bx R
bx Q
bx P
bx O
bx N
bx M
b0xxxxxxxxxxxxxxxxxxxxxxxxxx L
bx K
bx J
bx I
bx H
b11111111111111111111111111111111 G
b11111111111111111111111111111111 F
bx E
b11111 D
bx C
bx B
b11111111111111111111111111111111 A
b1111 @
b0 ?
bx >
b11111111111111111111111111111111 =
bx <
bx ;
bx :
bx 9
bx 8
bx 7
bx 6
bx 5
b0xxxxxxxxxxxxxxxxxxxxxxxxxxxxxx 4
bx 3
bx 2
bx 1
bx 0
b11111111111111111111111111111111 /
bx .
b0xxxxxxxx -
bx ,
b0 +
1*
b11111111111111111111111111111111 )
bx (
bx '
bx &
bx %
bx $
0#
1"
0!
$end
#10
b10100 C
b10100 )
b10100 =
b10100 s
b10100 G
b10100 F
b10100 8
b101 \
b101 `
b101 d
b101 h
b10100 /
b10100 A
b0 D
b1 Z
b0 U
b10100 T
b1 S
b101 4
b10100 I
b1 J
0t
b1 +
b1 ?
b1 r
b1 Y
b0 W
b1 X
b1 V
b10000000000010100 L
b10101 M
b0 Q
b1 P
b0 B
b0 E
b1 7
b0 >
b10100 9
b10101 0
b10100 2
b10000000000010100 .
b1 o
b0 n
b0 '
b0 ;
b0 p
b1 %
b1 5
b1 l
b1 O
b1 N
b0 K
b0 -
b100000000010000000000010100 $
b100000000010000000000010100 ,
b100000000010000000000010100 3
b0 m
b1 6
b0 &
b0 :
0"
0*
#30
1"
1*
#50
b1 )
b1 =
b1 s
b1 G
b1 F
b1 /
b1 A
b1 C
b0 \
b0 `
b0 d
b0 h
b1 T
b1 8
b0 4
b1 I
b10 +
b10 ?
b10 r
b10 Y
b10 X
b100000000000000001 L
b1 9
b1 2
b100000000000000001 .
b10 o
bx k
bx g
bx c
bx _
b10 %
b10 5
b10 l
b10 O
b10 N
b11 M
bx R
b1 K
b1 -
b100000000100000000000000001 $
b100000000100000000000000001 ,
b100000000100000000000000001 3
bx (
bx <
bx q
b1 m
b11 0
b10 6
b1 &
b1 :
1!
1#
#100
0!
0#
#150
b0 )
b0 =
b0 s
b0 G
b0 F
b0 /
b0 A
b0 C
b0 T
b0 8
b0 I
b11 +
b11 ?
b11 r
b11 Y
b11 X
b110000000000000000 L
b0 9
b0 2
b110000000000000000 .
b11 o
b10 K
b10 -
b100000000110000000000000000 $
b100000000110000000000000000 ,
b100000000110000000000000000 3
b11 %
b11 5
b11 l
b11 O
b11 N
b11 M
bx R
bx k
bx g
bx c
bx _
b10 m
b11 0
b11 6
b10 &
b10 :
bx (
bx <
bx q
1!
1#
#200
0!
0#
#250
b0 C
b101 \
b101 `
b101 d
b101 h
b0 S
b0 Z
b0 8
b10100 )
b10100 =
b10100 s
b10100 G
b1100000000000 I
b10100 F
b0 J
b11 W
b0 V
b1000110001100000000000 L
b10100 Q
b0 P
b11000000101 4
b10100 /
b10100 A
b10100 B
b0 7
b1100000000000 2
b1000110001100000000000 .
b1 n
b10100 '
b10100 ;
b10100 p
b0 k
b0 g
b0 c
b0 _
b100 %
b100 5
b100 l
b100 O
b100 N
b1100000000100 M
b0 R
b11 K
b11 -
b1000110001100000000000 $
b1000110001100000000000 ,
b1000110001100000000000 3
b0 (
b0 <
b0 q
b11 m
b1100000000100 0
b100 6
b11 &
b11 :
1!
1#
#300
0!
0#
#350
b10100 D
b11111111 \
b11111111 `
b11111111 d
b11111111 h
b100100 Z
b10100 U
b11110 T
b100100 S
b1 +
b1 ?
b1 r
b1 Y
b11111 W
b1 X
b100100 V
b10000011111111111111110 L
b1 Q
b100100 P
b111111111111111111111111111111 4
b1 B
b11111 E
b10011 )
b10011 =
b10011 s
b10011 G
b11111111111111111111111111111110 I
b10011 F
b100100 J
b100100 7
b11111 >
b11110 9
b11111111111111111111111111111110 2
b10000011111111111111110 .
b1 o
b10 n
b1 '
b1 ;
b1 p
b10011 /
b10011 A
b10100 C
b100 K
b100 -
b10010000010000011111111111111110 $
b10010000010000011111111111111110 ,
b10010000010000011111111111111110 3
b11 %
b11 5
b11 l
b11 O
b101 N
b11 M
b10100 R
b10100 _
b10100 8
b100 m
b11 0
b101 6
b100 &
b100 :
b10100 (
b10100 <
b10100 q
1!
1#
#400
0!
0#
#450
b0 D
b100 \
b100 `
b100 d
b100 h
b0 Z
b0 U
b0 T
b0 S
b100111 )
b100111 =
b100111 s
b100111 G
b1100000000000 I
b100111 F
b0 J
b11 +
b11 ?
b11 r
b11 Y
b11 W
b11 X
b0 V
b1000110001100000000000 L
b10011 Q
b0 P
b11000000100 4
b100111 /
b100111 A
b10100 C
b10011 B
b0 E
b0 7
b0 >
b0 9
b1100000000000 2
b1000110001100000000000 .
b11 o
b1 n
b10011 '
b10011 ;
b10011 p
b10100 _
b10100 8
b100 %
b100 5
b100 l
b100 O
b100 N
b1100000000100 M
b10100 R
b11 K
b11 -
b1000110001100000000000 $
b1000110001100000000000 ,
b1000110001100000000000 3
b10100 (
b10100 <
b10100 q
b11 m
b1100000000100 0
b100 6
b11 &
b11 :
1!
1#
#500
0!
0#
#550
b10100 D
b11111111 \
b11111111 `
b11111111 d
b11111111 h
b100100 Z
b10100 U
b11110 T
b100100 S
b1 +
b1 ?
b1 r
b1 Y
b11111 W
b1 X
b100100 V
b10000011111111111111110 L
b1 Q
b100100 P
b111111111111111111111111111111 4
b1 B
b11111 E
b10010 )
b10010 =
b10010 s
b10010 G
b11111111111111111111111111111110 I
b10010 F
b100100 J
b100100 7
b11111 >
b11110 9
b11111111111111111111111111111110 2
b10000011111111111111110 .
b1 o
b10 n
b1 '
b1 ;
b1 p
b10010 /
b10010 A
b10011 C
b100 K
b100 -
b10010000010000011111111111111110 $
b10010000010000011111111111111110 ,
b10010000010000011111111111111110 3
b11 %
b11 5
b11 l
b11 O
b101 N
b11 M
b10011 R
b10011 _
b10011 8
b100 m
b11 0
b101 6
b100 &
b100 :
b10011 (
b10011 <
b10011 q
1!
1#
#600
0!
0#
#650
b0 D
b100 \
b100 `
b100 d
b100 h
b0 Z
b0 U
b0 T
b0 S
b111001 )
b111001 =
b111001 s
b111001 G
b1100000000000 I
b111001 F
b0 J
b11 +
b11 ?
b11 r
b11 Y
b11 W
b11 X
b0 V
b1000110001100000000000 L
b10010 Q
b0 P
b11000000100 4
b111001 /
b111001 A
b100111 C
b10010 B
b0 E
b0 7
b0 >
b0 9
b1100000000000 2
b1000110001100000000000 .
b11 o
b1 n
b10010 '
b10010 ;
b10010 p
b100111 _
b100111 8
b100 %
b100 5
b100 l
b100 O
b100 N
b1100000000100 M
b100111 R
b11 K
b11 -
b1000110001100000000000 $
b1000110001100000000000 ,
b1000110001100000000000 3
b100111 (
b100111 <
b100111 q
b11 m
b1100000000100 0
b100 6
b11 &
b11 :
1!
1#
#700
0!
0#
#750
b10100 D
b11111111 \
b11111111 `
b11111111 d
b11111111 h
b100100 Z
b10100 U
b11110 T
b100100 S
b1 +
b1 ?
b1 r
b1 Y
b11111 W
b1 X
b100100 V
b10000011111111111111110 L
b1 Q
b100100 P
b111111111111111111111111111111 4
b1 B
b11111 E
b10001 )
b10001 =
b10001 s
b10001 G
b11111111111111111111111111111110 I
b10001 F
b100100 J
b100100 7
b11111 >
b11110 9
b11111111111111111111111111111110 2
b10000011111111111111110 .
b1 o
b10 n
b1 '
b1 ;
b1 p
b10001 /
b10001 A
b10010 C
b100 K
b100 -
b10010000010000011111111111111110 $
b10010000010000011111111111111110 ,
b10010000010000011111111111111110 3
b11 %
b11 5
b11 l
b11 O
b101 N
b11 M
b10010 R
b10010 _
b10010 8
b100 m
b11 0
b101 6
b100 &
b100 :
b10010 (
b10010 <
b10010 q
1!
1#
#800
0!
0#
#850
b0 D
b100 \
b100 `
b100 d
b100 h
b0 Z
b0 U
b0 T
b0 S
b1001010 )
b1001010 =
b1001010 s
b1001010 G
b1100000000000 I
b1001010 F
b0 J
b11 +
b11 ?
b11 r
b11 Y
b11 W
b11 X
b0 V
b1000110001100000000000 L
b10001 Q
b0 P
b11000000100 4
b1001010 /
b1001010 A
b111001 C
b10001 B
b0 E
b0 7
b0 >
b0 9
b1100000000000 2
b1000110001100000000000 .
b11 o
b1 n
b10001 '
b10001 ;
b10001 p
b111001 _
b111001 8
b100 %
b100 5
b100 l
b100 O
b100 N
b1100000000100 M
b111001 R
b11 K
b11 -
b1000110001100000000000 $
b1000110001100000000000 ,
b1000110001100000000000 3
b111001 (
b111001 <
b111001 q
b11 m
b1100000000100 0
b100 6
b11 &
b11 :
1!
1#
#900
0!
0#
#950
b10100 D
b11111111 \
b11111111 `
b11111111 d
b11111111 h
b100100 Z
b10100 U
b11110 T
b100100 S
b1 +
b1 ?
b1 r
b1 Y
b11111 W
b1 X
b100100 V
b10000011111111111111110 L
b1 Q
b100100 P
b111111111111111111111111111111 4
b1 B
b11111 E
b10000 )
b10000 =
b10000 s
b10000 G
b11111111111111111111111111111110 I
b10000 F
b100100 J
b100100 7
b11111 >
b11110 9
b11111111111111111111111111111110 2
b10000011111111111111110 .
b1 o
b10 n
b1 '
b1 ;
b1 p
b10000 /
b10000 A
b10001 C
b100 K
b100 -
b10010000010000011111111111111110 $
b10010000010000011111111111111110 ,
b10010000010000011111111111111110 3
b11 %
b11 5
b11 l
b11 O
b101 N
b11 M
b10001 R
b10001 _
b10001 8
b100 m
b11 0
b101 6
b100 &
b100 :
b10001 (
b10001 <
b10001 q
1!
1#
#1000
0!
0#
#1050
b0 D
b100 \
b100 `
b100 d
b100 h
b0 Z
b0 U
b0 T
b0 S
b1011010 )
b1011010 =
b1011010 s
b1011010 G
b1100000000000 I
b1011010 F
b0 J
b11 +
b11 ?
b11 r
b11 Y
b11 W
b11 X
b0 V
b1000110001100000000000 L
b10000 Q
b0 P
b11000000100 4
b1011010 /
b1011010 A
b1001010 C
b10000 B
b0 E
b0 7
b0 >
b0 9
b1100000000000 2
b1000110001100000000000 .
b11 o
b1 n
b10000 '
b10000 ;
b10000 p
b1001010 _
b1001010 8
b100 %
b100 5
b100 l
b100 O
b100 N
b1100000000100 M
b1001010 R
b11 K
b11 -
b1000110001100000000000 $
b1000110001100000000000 ,
b1000110001100000000000 3
b1001010 (
b1001010 <
b1001010 q
b11 m
b1100000000100 0
b100 6
b11 &
b11 :
1!
1#
#1100
0!
0#
#1150
b10100 D
b11111111 \
b11111111 `
b11111111 d
b11111111 h
b100100 Z
b10100 U
b11110 T
b100100 S
b1 +
b1 ?
b1 r
b1 Y
b11111 W
b1 X
b100100 V
b10000011111111111111110 L
b1 Q
b100100 P
b111111111111111111111111111111 4
b1 B
b11111 E
b1111 )
b1111 =
b1111 s
b1111 G
b11111111111111111111111111111110 I
b1111 F
b100100 J
b100100 7
b11111 >
b11110 9
b11111111111111111111111111111110 2
b10000011111111111111110 .
b1 o
b10 n
b1 '
b1 ;
b1 p
b1111 /
b1111 A
b10000 C
b100 K
b100 -
b10010000010000011111111111111110 $
b10010000010000011111111111111110 ,
b10010000010000011111111111111110 3
b11 %
b11 5
b11 l
b11 O
b101 N
b11 M
b10000 R
b10000 _
b10000 8
b100 m
b11 0
b101 6
b100 &
b100 :
b10000 (
b10000 <
b10000 q
1!
1#
#1200
0!
0#
#1250
b0 D
b11 \
b11 `
b11 d
b11 h
b0 Z
b0 U
b0 T
b0 S
b1101001 )
b1101001 =
b1101001 s
b1101001 G
b1100000000000 I
b1101001 F
b0 J
b11 +
b11 ?
b11 r
b11 Y
b11 W
b11 X
b0 V
b1000110001100000000000 L
b1111 Q
b0 P
b11000000011 4
b1101001 /
b1101001 A
b1011010 C
b1111 B
b0 E
b0 7
b0 >
b0 9
b1100000000000 2
b1000110001100000000000 .
b11 o
b1 n
b1111 '
b1111 ;
b1111 p
b1011010 _
b1011010 8
b100 %
b100 5
b100 l
b100 O
b100 N
b1100000000100 M
b1011010 R
b11 K
b11 -
b1000110001100000000000 $
b1000110001100000000000 ,
b1000110001100000000000 3
b1011010 (
b1011010 <
b1011010 q
b11 m
b1100000000100 0
b100 6
b11 &
b11 :
1!
1#
#1300
0!
0#
#1350
b10100 D
b11111111 \
b11111111 `
b11111111 d
b11111111 h
b100100 Z
b10100 U
b11110 T
b100100 S
b1 +
b1 ?
b1 r
b1 Y
b11111 W
b1 X
b100100 V
b10000011111111111111110 L
b1 Q
b100100 P
b111111111111111111111111111111 4
b1 B
b11111 E
b1110 )
b1110 =
b1110 s
b1110 G
b11111111111111111111111111111110 I
b1110 F
b100100 J
b100100 7
b11111 >
b11110 9
b11111111111111111111111111111110 2
b10000011111111111111110 .
b1 o
b10 n
b1 '
b1 ;
b1 p
b1110 /
b1110 A
b1111 C
b100 K
b100 -
b10010000010000011111111111111110 $
b10010000010000011111111111111110 ,
b10010000010000011111111111111110 3
b11 %
b11 5
b11 l
b11 O
b101 N
b11 M
b1111 R
b1111 _
b1111 8
b100 m
b11 0
b101 6
b100 &
b100 :
b1111 (
b1111 <
b1111 q
1!
1#
#1400
0!
0#
#1450
b0 D
b11 \
b11 `
b11 d
b11 h
b0 Z
b0 U
b0 T
b0 S
b1110111 )
b1110111 =
b1110111 s
b1110111 G
b1100000000000 I
b1110111 F
b0 J
b11 +
b11 ?
b11 r
b11 Y
b11 W
b11 X
b0 V
b1000110001100000000000 L
b1110 Q
b0 P
b11000000011 4
b1110111 /
b1110111 A
b1101001 C
b1110 B
b0 E
b0 7
b0 >
b0 9
b1100000000000 2
b1000110001100000000000 .
b11 o
b1 n
b1110 '
b1110 ;
b1110 p
b1101001 _
b1101001 8
b100 %
b100 5
b100 l
b100 O
b100 N
b1100000000100 M
b1101001 R
b11 K
b11 -
b1000110001100000000000 $
b1000110001100000000000 ,
b1000110001100000000000 3
b1101001 (
b1101001 <
b1101001 q
b11 m
b1100000000100 0
b100 6
b11 &
b11 :
1!
1#
#1500
0!
0#
#1550
b10100 D
b11111111 \
b11111111 `
b11111111 d
b11111111 h
b100100 Z
b10100 U
b11110 T
b100100 S
b1 +
b1 ?
b1 r
b1 Y
b11111 W
b1 X
b100100 V
b10000011111111111111110 L
b1 Q
b100100 P
b111111111111111111111111111111 4
b1 B
b11111 E
b1101 )
b1101 =
b1101 s
b1101 G
b11111111111111111111111111111110 I
b1101 F
b100100 J
b100100 7
b11111 >
b11110 9
b11111111111111111111111111111110 2
b10000011111111111111110 .
b1 o
b10 n
b1 '
b1 ;
b1 p
b1101 /
b1101 A
b1110 C
b100 K
b100 -
b10010000010000011111111111111110 $
b10010000010000011111111111111110 ,
b10010000010000011111111111111110 3
b11 %
b11 5
b11 l
b11 O
b101 N
b11 M
b1110 R
b1110 _
b1110 8
b100 m
b11 0
b101 6
b100 &
b100 :
b1110 (
b1110 <
b1110 q
1!
1#
#1600
0!
0#
#1650
b0 D
b11 \
b11 `
b11 d
b11 h
b0 Z
b0 U
b0 T
b0 S
b10000100 )
b10000100 =
b10000100 s
b10000100 G
b1100000000000 I
b10000100 F
b0 J
b11 +
b11 ?
b11 r
b11 Y
b11 W
b11 X
b0 V
b1000110001100000000000 L
b1101 Q
b0 P
b11000000011 4
b10000100 /
b10000100 A
b1110111 C
b1101 B
b0 E
b0 7
b0 >
b0 9
b1100000000000 2
b1000110001100000000000 .
b11 o
b1 n
b1101 '
b1101 ;
b1101 p
b1110111 _
b1110111 8
b100 %
b100 5
b100 l
b100 O
b100 N
b1100000000100 M
b1110111 R
b11 K
b11 -
b1000110001100000000000 $
b1000110001100000000000 ,
b1000110001100000000000 3
b1110111 (
b1110111 <
b1110111 q
b11 m
b1100000000100 0
b100 6
b11 &
b11 :
1!
1#
#1700
0!
0#
#1750
b10100 D
b11111111 \
b11111111 `
b11111111 d
b11111111 h
b100100 Z
b10100 U
b11110 T
b100100 S
b1 +
b1 ?
b1 r
b1 Y
b11111 W
b1 X
b100100 V
b10000011111111111111110 L
b1 Q
b100100 P
b111111111111111111111111111111 4
b1 B
b11111 E
b1100 )
b1100 =
b1100 s
b1100 G
b11111111111111111111111111111110 I
b1100 F
b100100 J
b100100 7
b11111 >
b11110 9
b11111111111111111111111111111110 2
b10000011111111111111110 .
b1 o
b10 n
b1 '
b1 ;
b1 p
b1100 /
b1100 A
b1101 C
b100 K
b100 -
b10010000010000011111111111111110 $
b10010000010000011111111111111110 ,
b10010000010000011111111111111110 3
b11 %
b11 5
b11 l
b11 O
b101 N
b11 M
b1101 R
b1101 _
b1101 8
b100 m
b11 0
b101 6
b100 &
b100 :
b1101 (
b1101 <
b1101 q
1!
1#
#1800
0!
0#
#1850
b0 D
b11 \
b11 `
b11 d
b11 h
b0 Z
b0 U
b0 T
b0 S
b10010000 )
b10010000 =
b10010000 s
b10010000 G
b1100000000000 I
b10010000 F
b0 J
b11 +
b11 ?
b11 r
b11 Y
b11 W
b11 X
b0 V
b1000110001100000000000 L
b1100 Q
b0 P
b11000000011 4
b10010000 /
b10010000 A
b10000100 C
b1100 B
b0 E
b0 7
b0 >
b0 9
b1100000000000 2
b1000110001100000000000 .
b11 o
b1 n
b1100 '
b1100 ;
b1100 p
b10000100 _
b10000100 8
b100 %
b100 5
b100 l
b100 O
b100 N
b1100000000100 M
b10000100 R
b11 K
b11 -
b1000110001100000000000 $
b1000110001100000000000 ,
b1000110001100000000000 3
b10000100 (
b10000100 <
b10000100 q
b11 m
b1100000000100 0
b100 6
b11 &
b11 :
1!
1#
#1900
0!
0#
#1950
b10100 D
b11111111 \
b11111111 `
b11111111 d
b11111111 h
b100100 Z
b10100 U
b11110 T
b100100 S
b1 +
b1 ?
b1 r
b1 Y
b11111 W
b1 X
b100100 V
b10000011111111111111110 L
b1 Q
b100100 P
b111111111111111111111111111111 4
b1 B
b11111 E
b1011 )
b1011 =
b1011 s
b1011 G
b11111111111111111111111111111110 I
b1011 F
b100100 J
b100100 7
b11111 >
b11110 9
b11111111111111111111111111111110 2
b10000011111111111111110 .
b1 o
b10 n
b1 '
b1 ;
b1 p
b1011 /
b1011 A
b1100 C
b100 K
b100 -
b10010000010000011111111111111110 $
b10010000010000011111111111111110 ,
b10010000010000011111111111111110 3
b11 %
b11 5
b11 l
b11 O
b101 N
b11 M
b1100 R
b1100 _
b1100 8
b100 m
b11 0
b101 6
b100 &
b100 :
b1100 (
b1100 <
b1100 q
1!
1#
#2000
0!
0#
#2050
b0 D
b10 \
b10 `
b10 d
b10 h
b0 Z
b0 U
b0 T
b0 S
b10011011 )
b10011011 =
b10011011 s
b10011011 G
b1100000000000 I
b10011011 F
b0 J
b11 +
b11 ?
b11 r
b11 Y
b11 W
b11 X
b0 V
b1000110001100000000000 L
b1011 Q
b0 P
b11000000010 4
b10011011 /
b10011011 A
b10010000 C
b1011 B
b0 E
b0 7
b0 >
b0 9
b1100000000000 2
b1000110001100000000000 .
b11 o
b1 n
b1011 '
b1011 ;
b1011 p
b10010000 _
b10010000 8
b100 %
b100 5
b100 l
b100 O
b100 N
b1100000000100 M
b10010000 R
b11 K
b11 -
b1000110001100000000000 $
b1000110001100000000000 ,
b1000110001100000000000 3
b10010000 (
b10010000 <
b10010000 q
b11 m
b1100000000100 0
b100 6
b11 &
b11 :
1!
1#
#2100
0!
0#
