HWDesign2016/0520/alu20.v
module  alu(A,B,O,CTR,ck);
input	[7:0]	A, B;
input	[3:0]	CTR;
input	ck;
output	[7:0] O;
reg	[7:0]	INA, INB, OUT, O;
reg	[3:0]	C;

always @(posedge ck) begin
	C <= CTR;
	INA <= A;
	INB <= B;
	case  (C)
	'b0000 : O <= INA + INB;
	'b0001 : O <= INA - INB;
	'b1000 : O <= INA & INB;
	'b1001 : O <= INA | INB;
	'b1010 : O <= INA ^ INB;
	'b1011 : O <= ~INA;
	'b1100 : O <= INA>>1;
	'b1101 : O <= INA<<1;
	'b1110 : O <= {INA[0], INA[7:1]};
	'b1111 : O <= {INA[6:0], INA[7]};
	endcase
end

endmodule

HWDesign2016/0520/alutest.v
module  alutest;
reg	[7:0]	A, B;
reg	[3:0]	CTR;
reg	ck;
wire	[7:0] O;
initial begin
	ck=0;
	$dumpfile("alu.vcd");
	$dumpvars;
	$monitor( "%t\tA=%d, B=%d, CTR=%b, OUT=%d", $time, A, B, CTR, O );
	#400  $finish;
end
alu alu(A , B , O , CTR , ck);
always	#40	ck <= ~ck;
always @(negedge ck) begin
	A <= $random;
	B <= $random;
	CTR  <= 0;
end
endmodule

HWDesign2016/0520/alu.vcd
$date
	Fri May 20 17:22:39 2016
$end
$version
	Icarus Verilog
$end
$timescale
	1s
$end
$scope module alutest $end
$var wire 8 ! O [7:0] $end
$var reg 8 " A [7:0] $end
$var reg 8 # B [7:0] $end
$var reg 4 $ CTR [3:0] $end
$var reg 1 % ck $end
$scope module alu $end
$var wire 8 & A [7:0] $end
$var wire 8 ' B [7:0] $end
$var wire 4 ( CTR [3:0] $end
$var wire 1 ) ck $end
$var reg 4 * C [3:0] $end
$var reg 8 + INA [7:0] $end
$var reg 8 , INB [7:0] $end
$var reg 8 - O [7:0] $end
$upscope $end
$upscope $end
$enddefinitions $end
#0
$dumpvars
bx -
bx ,
bx +
bx *
0)
bx (
bx '
bx &
0%
bx $
bx #
bx "
bx !
$end
#40
1%
1)
#80
b0 $
b0 (
b10000001 #
b10000001 '
b100100 "
b100100 &
0%
0)
#120
b10000001 ,
b100100 +
b0 *
1%
1)
#160
b1100011 #
b1100011 '
b1001 "
b1001 &
0%
0)
#200
b10100101 -
b10100101 !
b1100011 ,
b1001 +
1%
1)
#240
b10001101 #
b10001101 '
b1101 "
b1101 &
0%
0)
#280
b1101100 -
b1101100 !
b10001101 ,
b1101 +
1%
1)
#320
b10010 #
b10010 '
b1100101 "
b1100101 &
0%
0)
#360
b10011010 -
b10011010 !
b10010 ,
b1100101 +
1%
1)
