HWDesign2016/0520/fifo.v
module fifo ( Din, Dout, Wen, Ren, rst, ck, Fempty, Ffull );
input [7:0] Din;
output [7:0] Dout;
input Wen, Ren, rst, ck;
output Fempty, Ffull;

reg  [7:0] FMEM[0:15];
reg  [3:0] Wptr, Rptr;
reg  Fempty, Ffull;
reg  [7:0] obuf;
wire [3:0] NWptr, NRptr;

assign Dout = obuf;
assign NWptr = Wptr + 1;
assign NRptr = Rptr + 1;
wire  [7:0]  f0, f1, f2, f3, f4, f5, f6, f7, f8, f9, f10, f11, f12, f13, f14, f15;
assign f0 = FMEM[0];
assign f1 = FMEM[1];
assign f2 = FMEM[2];
assign f3 = FMEM[3];
assign f4 = FMEM[4];
assign f5 = FMEM[5];
assign f6 = FMEM[6];
assign f7 = FMEM[7];
assign f8 = FMEM[8];
assign f9 = FMEM[9];
assign f10 = FMEM[10];
assign f11 = FMEM[11];
assign f12 = FMEM[12];
assign f13 = FMEM[13];
assign f14 = FMEM[14];
assign f15 = FMEM[15];


always @(posedge ck) begin
   if( !rst ) begin
	Wptr <= 0;
   Rptr <= 0;
   Ffull <= 0;
	Fempty <= 1;
   end else begin
	if( Ren == 1 && Fempty != 1 ) begin
		obuf <= FMEM[Rptr];
		Rptr <= Rptr + 1;
		Ffull <= 0;
		if( NRptr == Wptr ) Fempty <= 1;
		else Fempty <= 0;
	end
	if( Wen == 1 && Ffull != 1 ) begin
		FMEM[Wptr] <= Din;
		Wptr <= Wptr + 1;
		Fempty <= 0;
		if( NWptr == Rptr ) Ffull <= 1;
		else Ffull <= 0;

	end
    end
end
endmodule

HWDesign2016/0520/simfifo.v
module top;
   reg[7:0] Din;
   wire [7:0] Dout;
   reg ck, rst, Wen, Ren, flag;
   wire Fempty, Ffull;

   fifo fifo( Din, Dout, Wen, Ren, rst, ck, Fempty, Ffull );

   initial begin
	ck = 0;
	rst = 1;
	$dumpfile( "fifo.vcd" );
	$dumpvars;
	#20 rst = 0;
	#50 rst = 1;
	#10000
      $finish;
   end

   always @(negedge ck)begin
     flag = $random;
     if( flag == 1 )begin
	Wen <= 1;
	Ren <= 0;
	Din = $random;
     end else begin
	Wen <= 0;
	Ren <= 1;
     end
   end

   always #10 ck <= ~ck;

endmodule

HWDesign2016/0520/fifo.vcd
$date
	Thu May 26 16:56:33 2016
$end
$version
	Icarus Verilog
$end
$timescale
	1s
$end
$scope module top $end
$var wire 8 ! Dout [7:0] $end
$var wire 1 " Fempty $end
$var wire 1 # Ffull $end
$var reg 8 $ Din [7:0] $end
$var reg 1 % Ren $end
$var reg 1 & Wen $end
$var reg 1 ' ck $end
$var reg 1 ( flag $end
$var reg 1 ) rst $end
$scope module fifo $end
$var wire 8 * Din [7:0] $end
$var wire 8 + Dout [7:0] $end
$var wire 4 , NRptr [3:0] $end
$var wire 4 - NWptr [3:0] $end
$var wire 1 . Ren $end
$var wire 1 / Wen $end
$var wire 1 0 ck $end
$var wire 8 1 f0 [7:0] $end
$var wire 8 2 f1 [7:0] $end
$var wire 8 3 f10 [7:0] $end
$var wire 8 4 f11 [7:0] $end
$var wire 8 5 f12 [7:0] $end
$var wire 8 6 f13 [7:0] $end
$var wire 8 7 f14 [7:0] $end
$var wire 8 8 f15 [7:0] $end
$var wire 8 9 f2 [7:0] $end
$var wire 8 : f3 [7:0] $end
$var wire 8 ; f4 [7:0] $end
$var wire 8 < f5 [7:0] $end
$var wire 8 = f6 [7:0] $end
$var wire 8 > f7 [7:0] $end
$var wire 8 ? f8 [7:0] $end
$var wire 8 @ f9 [7:0] $end
$var wire 1 A rst $end
$var reg 1 B Fempty $end
$var reg 1 C Ffull $end
$var reg 4 D Rptr [3:0] $end
$var reg 4 E Wptr [3:0] $end
$var reg 8 F obuf [7:0] $end
$upscope $end
$upscope $end
$enddefinitions $end
#0
$dumpvars
bx F
bx E
bx D
xC
xB
1A
bz @
bz ?
bz >
bz =
bz <
bz ;
bz :
bz 9
bz 8
bz 7
bz 6
bz 5
bz 4
bz 3
bz 2
bz 1
00
x/
x.
bx -
bx ,
bx +
bx *
1)
x(
0'
x&
x%
bx $
x#
x"
bx !
$end
#10
1'
10
#20
1%
1.
0&
0/
0(
0'
00
0)
0A
#30
b1 ,
b1 -
1B
1"
0C
0#
b0 D
b0 E
1'
10
#40
0%
0.
1&
1/
b1001 $
b1001 *
1(
0'
00
#50
1'
10
#60
b1101 $
b1101 *
0'
00
#70
b10 -
0B
0"
b1 E
b1101 1
1'
10
1)
1A
#80
b1100101 $
b1100101 *
0'
00
#90
b11 -
b10 E
b1100101 2
1'
10
#100
1%
1.
0&
0/
0(
0'
00
#110
b10 ,
b1 D
b1101 F
b1101 !
b1101 +
1'
10
#120
0%
0.
1&
1/
b1101 $
b1101 *
1(
0'
00
#130
b100 -
b11 E
b1101 9
1'
10
#140
1%
1.
0&
0/
0(
0'
00
#150
b11 ,
b10 D
b1100101 F
b1100101 !
b1100101 +
1'
10
#160
0%
0.
1&
1/
b11101101 $
b11101101 *
1(
0'
00
#170
b101 -
b100 E
b11101101 :
1'
10
#180
1%
1.
0&
0/
0(
0'
00
#190
b100 ,
b11 D
b1101 F
b1101 !
b1101 +
1'
10
#200
0%
0.
1&
1/
b11000110 $
b11000110 *
1(
0'
00
#210
b110 -
b101 E
b11000110 ;
1'
10
#220
b10101010 $
b10101010 *
0'
00
#230
b111 -
b110 E
b10101010 <
1'
10
#240
b1110111 $
b1110111 *
0'
00
#250
b1000 -
b111 E
b1110111 =
1'
10
#260
1%
1.
0&
0/
0(
0'
00
#270
b101 ,
b100 D
b11101101 F
b11101101 !
b11101101 +
1'
10
#280
0%
0.
1&
1/
b11110010 $
b11110010 *
1(
0'
00
#290
b1001 -
b1000 E
b11110010 >
1'
10
#300
1%
1.
0&
0/
0(
0'
00
#310
b110 ,
b101 D
b11000110 F
b11000110 !
b11000110 +
1'
10
#320
0'
00
#330
b111 ,
b110 D
b10101010 F
b10101010 !
b10101010 +
1'
10
#340
0%
0.
1&
1/
b1011100 $
b1011100 *
1(
0'
00
#350
b1010 -
b1001 E
b1011100 ?
1'
10
#360
b101101 $
b101101 *
0'
00
#370
b1011 -
b1010 E
b101101 @
1'
10
#380
b1100011 $
b1100011 *
0'
00
#390
b1100 -
b1011 E
b1100011 3
1'
10
#400
1%
1.
0&
0/
0(
0'
00
#410
b1000 ,
b111 D
b1110111 F
b1110111 !
b1110111 +
1'
10
#420
0'
00
#430
b1001 ,
b1000 D
b11110010 F
b11110010 !
b11110010 +
1'
10
#440
0'
00
#450
b1010 ,
b1001 D
b1011100 F
b1011100 !
b1011100 +
1'
10
#460
0'
00
#470
b1011 ,
b1010 D
b101101 F
b101101 !
b101101 +
1'
10
#480
0%
0.
1&
1/
b10010110 $
b10010110 *
1(
0'
00
#490
b1101 -
b1100 E
b10010110 4
1'
10
#500
b1101 $
b1101 *
0'
00
#510
b1110 -
b1101 E
b1101 5
1'
10
#520
b1101011 $
b1101011 *
0'
00
#530
b1111 -
b1110 E
b1101011 6
1'
10
#540
b10 $
b10 *
0'
00
#550
b0 -
b1111 E
b10 7
1'
10
#560
1%
1.
0&
0/
0(
0'
00
#570
b1100 ,
b1011 D
b1100011 F
b1100011 !
b1100011 +
1'
10
#580
0%
0.
1&
1/
b11001111 $
b11001111 *
1(
0'
00
#590
b1 -
b0 E
b11001111 8
1'
10
#600
b1010 $
b1010 *
0'
00
#610
b10 -
b1 E
b1010 1
1'
10
#620
1%
1.
0&
0/
0(
0'
00
#630
b1101 ,
b1100 D
b10010110 F
b10010110 !
b10010110 +
1'
10
#640
0'
00
#650
b1110 ,
b1101 D
b1101 F
b1101 !
b1101 +
1'
10
#660
0'
00
#670
b1111 ,
b1110 D
b1101011 F
b1101011 !
b1101011 +
1'
10
#680
0'
00
#690
b0 ,
b1111 D
b10 F
b10 !
b10 +
1'
10
#700
0%
0.
1&
1/
b11011000 $
b11011000 *
1(
0'
00
#710
b11 -
b10 E
b11011000 2
1'
10
#720
1%
1.
0&
0/
0(
0'
00
#730
b1 ,
b0 D
b11001111 F
b11001111 !
b11001111 +
1'
10
#740
0%
0.
1&
1/
b11101011 $
b11101011 *
1(
0'
00
#750
b100 -
b11 E
b11101011 9
1'
10
#760
1%
1.
0&
0/
0(
0'
00
#770
b10 ,
b1 D
b1010 F
b1010 !
b1010 +
1'
10
#780
0'
00
#790
b11 ,
b10 D
b11011000 F
b11011000 !
b11011000 +
1'
10
#800
0'
00
#810
b100 ,
1B
1"
b11 D
b11101011 F
b11101011 !
b11101011 +
1'
10
#820
0'
00
#830
1'
10
#840
0'
00
#850
1'
10
#860
0%
0.
1&
1/
b1110001 $
b1110001 *
1(
0'
00
#870
b101 -
0B
0"
b100 E
b1110001 :
1'
10
#880
b1001111 $
b1001111 *
0'
00
#890
b110 -
b101 E
b1001111 ;
1'
10
#900
b111010 $
b111010 *
0'
00
#910
b111 -
b110 E
b111010 <
1'
10
#920
1%
1.
0&
0/
0(
0'
00
#930
b101 ,
b100 D
b1110001 F
b1110001 !
b1110001 +
1'
10
#940
0%
0.
1&
1/
b11110001 $
b11110001 *
1(
0'
00
#950
b1000 -
b111 E
b11110001 =
1'
10
#960
b1100010 $
b1100010 *
0'
00
#970
b1001 -
b1000 E
b1100010 >
1'
10
#980
1%
1.
0&
0/
0(
0'
00
#990
b110 ,
b101 D
b1001111 F
b1001111 !
b1001111 +
1'
10
#1000
0%
0.
1&
1/
b10001111 $
b10001111 *
1(
0'
00
#1010
b1010 -
b1001 E
b10001111 ?
1'
10
#1020
1%
1.
0&
0/
0(
0'
00
#1030
b111 ,
b110 D
b111010 F
b111010 !
b111010 +
1'
10
#1040
0%
0.
1&
1/
b10011111 $
b10011111 *
1(
0'
00
#1050
b1011 -
b1010 E
b10011111 @
1'
10
#1060
1%
1.
0&
0/
0(
0'
00
#1070
b1000 ,
b111 D
b11110001 F
b11110001 !
b11110001 +
1'
10
#1080
0%
0.
1&
1/
b10001001 $
b10001001 *
1(
0'
00
#1090
b1100 -
b1011 E
b10001001 3
1'
10
#1100
b11010000 $
b11010000 *
0'
00
#1110
b1101 -
b1100 E
b11010000 4
1'
10
#1120
b1010001 $
b1010001 *
0'
00
#1130
b1110 -
b1101 E
b1010001 5
1'
10
#1140
1%
1.
0&
0/
0(
0'
00
#1150
b1001 ,
b1000 D
b1100010 F
b1100010 !
b1100010 +
1'
10
#1160
0'
00
#1170
b1010 ,
b1001 D
b10001111 F
b10001111 !
b10001111 +
1'
10
#1180
0'
00
#1190
b1011 ,
b1010 D
b10011111 F
b10011111 !
b10011111 +
1'
10
#1200
0'
00
#1210
b1100 ,
b1011 D
b10001001 F
b10001001 !
b10001001 +
1'
10
#1220
0%
0.
1&
1/
b111101 $
b111101 *
1(
0'
00
#1230
b1111 -
b1110 E
b111101 6
1'
10
#1240
1%
1.
0&
0/
0(
0'
00
#1250
b1101 ,
b1100 D
b11010000 F
b11010000 !
b11010000 +
1'
10
#1260
0'
00
#1270
b1110 ,
b1101 D
b1010001 F
b1010001 !
b1010001 +
1'
10
#1280
0%
0.
1&
1/
b111001 $
b111001 *
1(
0'
00
#1290
b0 -
b1111 E
b111001 7
1'
10
#1300
b11010011 $
b11010011 *
0'
00
#1310
b1 -
b0 E
b11010011 8
1'
10
#1320
b1111000 $
b1111000 *
0'
00
#1330
b10 -
b1 E
b1111000 1
1'
10
#1340
b1001001 $
b1001001 *
0'
00
#1350
b11 -
b10 E
b1001001 2
1'
10
#1360
b101010 $
b101010 *
0'
00
#1370
b100 -
b11 E
b101010 9
1'
10
#1380
1%
1.
0&
0/
0(
0'
00
#1390
b1111 ,
b1110 D
b111101 F
b111101 !
b111101 +
1'
10
#1400
0'
00
#1410
b0 ,
b1111 D
b111001 F
b111001 !
b111001 +
1'
10
#1420
0'
00
#1430
b1 ,
b0 D
b11010011 F
b11010011 !
b11010011 +
1'
10
#1440
0'
00
#1450
b10 ,
b1 D
b1111000 F
b1111000 !
b1111000 +
1'
10
#1460
0'
00
#1470
b11 ,
b10 D
b1001001 F
b1001001 !
b1001001 +
1'
10
#1480
0'
00
#1490
b100 ,
1B
1"
b11 D
b101010 F
b101010 !
b101010 +
1'
10
#1500
0%
0.
1&
1/
b10100011 $
b10100011 *
1(
0'
00
#1510
b101 -
0B
0"
b100 E
b10100011 :
1'
10
#1520
b10110011 $
b10110011 *
0'
00
#1530
b110 -
b101 E
b10110011 ;
1'
10
#1540
b1000100 $
b1000100 *
0'
00
#1550
b111 -
b110 E
b1000100 <
1'
10
#1560
b11001011 $
b11001011 *
0'
00
#1570
b1000 -
b111 E
b11001011 =
1'
10
#1580
1%
1.
0&
0/
0(
0'
00
#1590
b101 ,
b100 D
b10100011 F
b10100011 !
b10100011 +
1'
10
#1600
0'
00
#1610
b110 ,
b101 D
b10110011 F
b10110011 !
b10110011 +
1'
10
#1620
0%
0.
1&
1/
b11101101 $
b11101101 *
1(
0'
00
#1630
b1001 -
b1000 E
b11101101 >
1'
10
#1640
1%
1.
0&
0/
0(
0'
00
#1650
b111 ,
b110 D
b1000100 F
b1000100 !
b1000100 +
1'
10
#1660
0%
0.
1&
1/
b10110101 $
b10110101 *
1(
0'
00
#1670
b1010 -
b1001 E
b10110101 ?
1'
10
#1680
b1111001 $
b1111001 *
0'
00
#1690
b1011 -
b1010 E
b1111001 @
1'
10
#1700
1%
1.
0&
0/
0(
0'
00
#1710
b1000 ,
b111 D
b11001011 F
b11001011 !
b11001011 +
1'
10
#1720
0'
00
#1730
b1001 ,
b1000 D
b11101101 F
b11101101 !
b11101101 +
1'
10
#1740
0'
00
#1750
b1010 ,
b1001 D
b10110101 F
b10110101 !
b10110101 +
1'
10
#1760
0%
0.
1&
1/
b1110 $
b1110 *
1(
0'
00
#1770
b1100 -
b1011 E
b1110 3
1'
10
#1780
1%
1.
0&
0/
0(
0'
00
#1790
b1011 ,
b1010 D
b1111001 F
b1111001 !
b1111001 +
1'
10
#1800
0'
00
#1810
b1100 ,
1B
1"
b1011 D
b1110 F
b1110 !
b1110 +
1'
10
#1820
0%
0.
1&
1/
b11000011 $
b11000011 *
1(
0'
00
#1830
b1101 -
0B
0"
b1100 E
b11000011 4
1'
10
#1840
1%
1.
0&
0/
0(
0'
00
#1850
b1101 ,
1B
1"
b1100 D
b11000011 F
b11000011 !
b11000011 +
1'
10
#1860
0'
00
#1870
1'
10
#1880
0%
0.
1&
1/
b1010 $
b1010 *
1(
0'
00
#1890
b1110 -
0B
0"
b1101 E
b1010 5
1'
10
#1900
1%
1.
0&
0/
0(
0'
00
#1910
b1110 ,
1B
1"
b1101 D
b1010 F
b1010 !
b1010 +
1'
10
#1920
0'
00
#1930
1'
10
#1940
0%
0.
1&
1/
b10111000 $
b10111000 *
1(
0'
00
#1950
b1111 -
0B
0"
b1110 E
b10111000 6
1'
10
#1960
1%
1.
0&
0/
0(
0'
00
#1970
b1111 ,
1B
1"
b1110 D
b10111000 F
b10111000 !
b10111000 +
1'
10
#1980
0%
0.
1&
1/
b100 $
b100 *
1(
0'
00
#1990
b0 -
0B
0"
b1111 E
b100 7
1'
10
#2000
b11011011 $
b11011011 *
0'
00
#2010
b1 -
b0 E
b11011011 8
1'
10
#2020
b11011001 $
b11011001 *
0'
00
#2030
b10 -
b1 E
b11011001 1
1'
10
#2040
b1110110 $
b1110110 *
0'
00
#2050
b11 -
b10 E
b1110110 2
1'
10
#2060
1%
1.
0&
0/
0(
0'
00
#2070
b0 ,
b1111 D
b100 F
b100 !
b100 +
1'
10
#2080
0'
00
#2090
b1 ,
b0 D
b11011011 F
b11011011 !
b11011011 +
1'
10
#2100
0%
0.
1&
1/
b1000110 $
b1000110 *
1(
0'
00
#2110
b100 -
b11 E
b1000110 9
1'
10
#2120
1%
1.
0&
0/
0(
0'
00
#2130
b10 ,
b1 D
b11011001 F
b11011001 !
b11011001 +
1'
10
#2140
0%
0.
1&
1/
b1101001 $
b1101001 *
1(
0'
00
#2150
b101 -
b100 E
b1101001 :
1'
10
#2160
1%
1.
0&
0/
0(
0'
00
#2170
b11 ,
b10 D
b1110110 F
b1110110 !
b1110110 +
1'
10
#2180
0'
00
#2190
b100 ,
b11 D
b1000110 F
b1000110 !
b1000110 +
1'
10
#2200
0'
00
#2210
b101 ,
1B
1"
b100 D
b1101001 F
b1101001 !
b1101001 +
1'
10
#2220
0%
0.
1&
1/
b11000111 $
b11000111 *
1(
0'
00
#2230
b110 -
0B
0"
b101 E
b11000111 ;
1'
10
#2240
1%
1.
0&
0/
0(
0'
00
#2250
b110 ,
1B
1"
b101 D
b11000111 F
b11000111 !
b11000111 +
1'
10
#2260
0'
00
#2270
1'
10
#2280
0'
00
#2290
1'
10
#2300
0%
0.
1&
1/
b101001 $
b101001 *
1(
0'
00
#2310
b111 -
0B
0"
b110 E
b101001 <
1'
10
#2320
1%
1.
0&
0/
0(
0'
00
#2330
b111 ,
1B
1"
b110 D
b101001 F
b101001 !
b101001 +
1'
10
#2340
0'
00
#2350
1'
10
#2360
0'
00
#2370
1'
10
#2380
0%
0.
1&
1/
b1100110 $
b1100110 *
1(
0'
00
#2390
b1000 -
0B
0"
b111 E
b1100110 =
1'
10
#2400
1%
1.
0&
0/
0(
0'
00
#2410
b1000 ,
1B
1"
b111 D
b1100110 F
b1100110 !
b1100110 +
1'
10
#2420
0%
0.
1&
1/
b10111010 $
b10111010 *
1(
0'
00
#2430
b1001 -
0B
0"
b1000 E
b10111010 >
1'
10
#2440
1%
1.
0&
0/
0(
0'
00
#2450
b1001 ,
1B
1"
b1000 D
b10111010 F
b10111010 !
b10111010 +
1'
10
#2460
0'
00
#2470
1'
10
#2480
0%
0.
1&
1/
b11010 $
b11010 *
1(
0'
00
#2490
b1010 -
0B
0"
b1001 E
b11010 ?
1'
10
#2500
b110111 $
b110111 *
0'
00
#2510
b1011 -
b1010 E
b110111 @
1'
10
#2520
1%
1.
0&
0/
0(
0'
00
#2530
b1010 ,
b1001 D
b11010 F
b11010 !
b11010 +
1'
10
#2540
0'
00
#2550
b1011 ,
1B
1"
b1010 D
b110111 F
b110111 !
b110111 +
1'
10
#2560
0'
00
#2570
1'
10
#2580
0'
00
#2590
1'
10
#2600
0%
0.
1&
1/
b11011100 $
b11011100 *
1(
0'
00
#2610
b1100 -
0B
0"
b1011 E
b11011100 3
1'
10
#2620
1%
1.
0&
0/
0(
0'
00
#2630
b1100 ,
1B
1"
b1011 D
b11011100 F
b11011100 !
b11011100 +
1'
10
#2640
0'
00
#2650
1'
10
#2660
0'
00
#2670
1'
10
#2680
0%
0.
1&
1/
b11001111 $
b11001111 *
1(
0'
00
#2690
b1101 -
0B
0"
b1100 E
b11001111 4
1'
10
#2700
b11111010 $
b11111010 *
0'
00
#2710
b1110 -
b1101 E
b11111010 5
1'
10
#2720
b10111 $
b10111 *
0'
00
#2730
b1111 -
b1110 E
b10111 6
1'
10
#2740
b10000110 $
b10000110 *
0'
00
#2750
b0 -
b1111 E
b10000110 7
1'
10
#2760
1%
1.
0&
0/
0(
0'
00
#2770
b1101 ,
b1100 D
b11001111 F
b11001111 !
b11001111 +
1'
10
#2780
0%
0.
1&
1/
b110101 $
b110101 *
1(
0'
00
#2790
b1 -
b0 E
b110101 8
1'
10
#2800
b11000001 $
b11000001 *
0'
00
#2810
b10 -
b1 E
b11000001 1
1'
10
#2820
b10011000 $
b10011000 *
0'
00
#2830
b11 -
b10 E
b10011000 2
1'
10
#2840
b1110011 $
b1110011 *
0'
00
#2850
b100 -
b11 E
b1110011 9
1'
10
#2860
1%
1.
0&
0/
0(
0'
00
#2870
b1110 ,
b1101 D
b11111010 F
b11111010 !
b11111010 +
1'
10
#2880
0'
00
#2890
b1111 ,
b1110 D
b10111 F
b10111 !
b10111 +
1'
10
#2900
0'
00
#2910
b0 ,
b1111 D
b10000110 F
b10000110 !
b10000110 +
1'
10
#2920
0'
00
#2930
b1 ,
b0 D
b110101 F
b110101 !
b110101 +
1'
10
#2940
0%
0.
1&
1/
b10100001 $
b10100001 *
1(
0'
00
#2950
b101 -
b100 E
b10100001 :
1'
10
#2960
1%
1.
0&
0/
0(
0'
00
#2970
b10 ,
b1 D
b11000001 F
b11000001 !
b11000001 +
1'
10
#2980
0'
00
#2990
b11 ,
b10 D
b10011000 F
b10011000 !
b10011000 +
1'
10
#3000
0%
0.
1&
1/
b101010 $
b101010 *
1(
0'
00
#3010
b110 -
b101 E
b101010 ;
1'
10
#3020
1%
1.
0&
0/
0(
0'
00
#3030
b100 ,
b11 D
b1110011 F
b1110011 !
b1110011 +
1'
10
#3040
0%
0.
1&
1/
b10011110 $
b10011110 *
1(
0'
00
#3050
b111 -
b110 E
b10011110 <
1'
10
#3060
1%
1.
0&
0/
0(
0'
00
#3070
b101 ,
b100 D
b10100001 F
b10100001 !
b10100001 +
1'
10
#3080
0%
0.
1&
1/
b11001000 $
b11001000 *
1(
0'
00
#3090
b1000 -
b111 E
b11001000 =
1'
10
#3100
1%
1.
0&
0/
0(
0'
00
#3110
b110 ,
b101 D
b101010 F
b101010 !
b101010 +
1'
10
#3120
0%
0.
1&
1/
b1101011 $
b1101011 *
1(
0'
00
#3130
b1001 -
b1000 E
b1101011 >
1'
10
#3140
b10110110 $
b10110110 *
0'
00
#3150
b1010 -
b1001 E
b10110110 ?
1'
10
#3160
1%
1.
0&
0/
0(
0'
00
#3170
b111 ,
b110 D
b10011110 F
b10011110 !
b10011110 +
1'
10
#3180
0'
00
#3190
b1000 ,
b111 D
b11001000 F
b11001000 !
b11001000 +
1'
10
#3200
0%
0.
1&
1/
b10010010 $
b10010010 *
1(
0'
00
#3210
b1011 -
b1010 E
b10010010 @
1'
10
#3220
1%
1.
0&
0/
0(
0'
00
#3230
b1001 ,
b1000 D
b1101011 F
b1101011 !
b1101011 +
1'
10
#3240
0%
0.
1&
1/
b10000110 $
b10000110 *
1(
0'
00
#3250
b1100 -
b1011 E
b10000110 3
1'
10
#3260
1%
1.
0&
0/
0(
0'
00
#3270
b1010 ,
b1001 D
b10110110 F
b10110110 !
b10110110 +
1'
10
#3280
0'
00
#3290
b1011 ,
b1010 D
b10010010 F
b10010010 !
b10010010 +
1'
10
#3300
0'
00
#3310
b1100 ,
1B
1"
b1011 D
b10000110 F
b10000110 !
b10000110 +
1'
10
#3320
0%
0.
1&
1/
b10000100 $
b10000100 *
1(
0'
00
#3330
b1101 -
0B
0"
b1100 E
b10000100 4
1'
10
#3340
1%
1.
0&
0/
0(
0'
00
#3350
b1101 ,
1B
1"
b1100 D
b10000100 F
b10000100 !
b10000100 +
1'
10
#3360
0'
00
#3370
1'
10
#3380
0%
0.
1&
1/
b10100001 $
b10100001 *
1(
0'
00
#3390
b1110 -
0B
0"
b1101 E
b10100001 5
1'
10
#3400
1%
1.
0&
0/
0(
0'
00
#3410
b1110 ,
1B
1"
b1101 D
b10100001 F
b10100001 !
b10100001 +
1'
10
#3420
0%
0.
1&
1/
b1011 $
b1011 *
1(
0'
00
#3430
b1111 -
0B
0"
b1110 E
b1011 6
1'
10
#3440
b11001001 $
b11001001 *
0'
00
#3450
b0 -
b1111 E
b11001001 7
1'
10
#3460
1%
1.
0&
0/
0(
0'
00
#3470
b1111 ,
b1110 D
b1011 F
b1011 !
b1011 +
1'
10
#3480
0%
0.
1&
1/
b10001111 $
b10001111 *
1(
0'
00
#3490
b1 -
b0 E
b10001111 8
1'
10
#3500
b10001000 $
b10001000 *
0'
00
#3510
b10 -
b1 E
b10001000 1
1'
10
#3520
1%
1.
0&
0/
0(
0'
00
#3530
b0 ,
b1111 D
b11001001 F
b11001001 !
b11001001 +
1'
10
#3540
0%
0.
1&
1/
b10010010 $
b10010010 *
1(
0'
00
#3550
b11 -
b10 E
b10010010 2
1'
10
#3560
1%
1.
0&
0/
0(
0'
00
#3570
b1 ,
b0 D
b10001111 F
b10001111 !
b10001111 +
1'
10
#3580
0%
0.
1&
1/
b1001011 $
b1001011 *
1(
0'
00
#3590
b100 -
b11 E
b1001011 9
1'
10
#3600
1%
1.
0&
0/
0(
0'
00
#3610
b10 ,
b1 D
b10001000 F
b10001000 !
b10001000 +
1'
10
#3620
0'
00
#3630
b11 ,
b10 D
b10010010 F
b10010010 !
b10010010 +
1'
10
#3640
0%
0.
1&
1/
b11101100 $
b11101100 *
1(
0'
00
#3650
b101 -
b100 E
b11101100 :
1'
10
#3660
1%
1.
0&
0/
0(
0'
00
#3670
b100 ,
b11 D
b1001011 F
b1001011 !
b1001011 +
1'
10
#3680
0%
0.
1&
1/
b10000110 $
b10000110 *
1(
0'
00
#3690
b110 -
b101 E
b10000110 ;
1'
10
#3700
b111011 $
b111011 *
0'
00
#3710
b111 -
b110 E
b111011 <
1'
10
#3720
1%
1.
0&
0/
0(
0'
00
#3730
b101 ,
b100 D
b11101100 F
b11101100 !
b11101100 +
1'
10
#3740
0%
0.
1&
1/
b1010110 $
b1010110 *
1(
0'
00
#3750
b1000 -
b111 E
b1010110 =
1'
10
#3760
b11100010 $
b11100010 *
0'
00
#3770
b1001 -
b1000 E
b11100010 >
1'
10
#3780
1%
1.
0&
0/
0(
0'
00
#3790
b110 ,
b101 D
b10000110 F
b10000110 !
b10000110 +
1'
10
#3800
0%
0.
1&
1/
b11011000 $
b11011000 *
1(
0'
00
#3810
b1010 -
b1001 E
b11011000 ?
1'
10
#3820
1%
1.
0&
0/
0(
0'
00
#3830
b111 ,
b110 D
b111011 F
b111011 !
b111011 +
1'
10
#3840
0'
00
#3850
b1000 ,
b111 D
b1010110 F
b1010110 !
b1010110 +
1'
10
#3860
0%
0.
1&
1/
b11100101 $
b11100101 *
1(
0'
00
#3870
b1011 -
b1010 E
b11100101 @
1'
10
#3880
b101011 $
b101011 *
0'
00
#3890
b1100 -
b1011 E
b101011 3
1'
10
#3900
b11001000 $
b11001000 *
0'
00
#3910
b1101 -
b1100 E
b11001000 4
1'
10
#3920
b10100001 $
b10100001 *
0'
00
#3930
b1110 -
b1101 E
1'
10
#3940
b100 $
b100 *
0'
00
#3950
b1111 -
b1110 E
b100 6
1'
10
#3960
1%
1.
0&
0/
0(
0'
00
#3970
b1001 ,
b1000 D
b11100010 F
b11100010 !
b11100010 +
1'
10
#3980
0'
00
#3990
b1010 ,
b1001 D
b11011000 F
b11011000 !
b11011000 +
1'
10
#4000
0'
00
#4010
b1011 ,
b1010 D
b11100101 F
b11100101 !
b11100101 +
1'
10
#4020
0'
00
#4030
b1100 ,
b1011 D
b101011 F
b101011 !
b101011 +
1'
10
#4040
0'
00
#4050
b1101 ,
b1100 D
b11001000 F
b11001000 !
b11001000 +
1'
10
#4060
0%
0.
1&
1/
b1010101 $
b1010101 *
1(
0'
00
#4070
b0 -
b1111 E
b1010101 7
1'
10
#4080
b101011 $
b101011 *
0'
00
#4090
b1 -
b0 E
b101011 8
1'
10
#4100
b10101101 $
b10101101 *
0'
00
#4110
b10 -
b1 E
b10101101 1
1'
10
#4120
b10000100 $
b10000100 *
0'
00
#4130
b11 -
b10 E
b10000100 2
1'
10
#4140
b11100111 $
b11100111 *
0'
00
#4150
b100 -
b11 E
b11100111 9
1'
10
#4160
b1001001 $
b1001001 *
0'
00
#4170
b101 -
b100 E
b1001001 :
1'
10
#4180
b11001001 $
b11001001 *
0'
00
#4190
b110 -
b101 E
b11001001 ;
1'
10
#4200
b10100001 $
b10100001 *
0'
00
#4210
b111 -
b110 E
b10100001 <
1'
10
#4220
1%
1.
0&
0/
0(
0'
00
#4230
b1110 ,
b1101 D
b10100001 F
b10100001 !
b10100001 +
1'
10
#4240
0'
00
#4250
b1111 ,
b1110 D
b100 F
b100 !
b100 +
1'
10
#4260
0%
0.
1&
1/
b10000011 $
b10000011 *
1(
0'
00
#4270
b1000 -
b111 E
b10000011 =
1'
10
#4280
1%
1.
0&
0/
0(
0'
00
#4290
b0 ,
b1111 D
b1010101 F
b1010101 !
b1010101 +
1'
10
#4300
0'
00
#4310
b1 ,
b0 D
b101011 F
b101011 !
b101011 +
1'
10
#4320
0'
00
#4330
b10 ,
b1 D
b10101101 F
b10101101 !
b10101101 +
1'
10
#4340
0'
00
#4350
b11 ,
b10 D
b10000100 F
b10000100 !
b10000100 +
1'
10
#4360
0%
0.
1&
1/
b10000110 $
b10000110 *
1(
0'
00
#4370
b1001 -
b1000 E
b10000110 >
1'
10
#4380
1%
1.
0&
0/
0(
0'
00
#4390
b100 ,
b11 D
b11100111 F
b11100111 !
b11100111 +
1'
10
#4400
0'
00
#4410
b101 ,
b100 D
b1001001 F
b1001001 !
b1001001 +
1'
10
#4420
0'
00
#4430
b110 ,
b101 D
b11001001 F
b11001001 !
b11001001 +
1'
10
#4440
0'
00
#4450
b111 ,
b110 D
b10100001 F
b10100001 !
b10100001 +
1'
10
#4460
0'
00
#4470
b1000 ,
b111 D
b10000011 F
b10000011 !
b10000011 +
1'
10
#4480
0%
0.
1&
1/
b11000000 $
b11000000 *
1(
0'
00
#4490
b1010 -
b1001 E
b11000000 ?
1'
10
#4500
1%
1.
0&
0/
0(
0'
00
#4510
b1001 ,
b1000 D
b10000110 F
b10000110 !
b10000110 +
1'
10
#4520
0%
0.
1&
1/
b10110000 $
b10110000 *
1(
0'
00
#4530
b1011 -
b1010 E
b10110000 @
1'
10
#4540
1%
1.
0&
0/
0(
0'
00
#4550
b1010 ,
b1001 D
b11000000 F
b11000000 !
b11000000 +
1'
10
#4560
0'
00
#4570
b1011 ,
1B
1"
b1010 D
b10110000 F
b10110000 !
b10110000 +
1'
10
#4580
0'
00
#4590
1'
10
#4600
0%
0.
1&
1/
b11100001 $
b11100001 *
1(
0'
00
#4610
b1100 -
0B
0"
b1011 E
b11100001 3
1'
10
#4620
b1000011 $
b1000011 *
0'
00
#4630
b1101 -
b1100 E
b1000011 4
1'
10
