HWDesign2016/0527/cpu.v
module CPU(CK,RST,IA,ID,DA,DD,RW);
input CK,RST;
input [15:0] ID;
output 	RW;
output [15:0] IA,DA;
inout [15:0]  DD;
reg [15:0] 	 PC, INST, FUA,
		FUB, LSUA, LSUB, FUC, LSUC, PCC, PCI;
reg [15:0] 	 RF[0:14];
reg [1:0] 	 STAGE;
reg 		 FLAG,RW;
wire [15:0] 	 ABUS, BBUS, CBUS;
wire [3:0] 	 OPCODE, OPR1,
		OPR2, OPR3;
wire [7:0] 	 IMM;
wire [15:0] 	 PCn;
assign PCn = PC + 1;

assign OPCODE = INST[15:12];
assign OPR1 = INST[11:8];
assign OPR2 = INST[7:4];
assign OPR3 = INST[3:0];
assign IMM = INST[7:0];
assign ABUS = (OPR2 == 0 ? 0 : RF[OPR2]);
assign BBUS = (OPR3 == 0 ? 0 : RF[OPR3]);
assign DA = LSUB;
assign IA = PC;
assign DD =((RW==0)? LSUA : 16'b Z);
assign CBUS = (OPCODE[3]==0 ? FUC : (OPCODE[3:1]=='b 101 ? LSUC :
		(OPCODE=='b 1100 ? {8'b 0,IMM} : OPCODE=='b 1000 ? PCC : 'b z)));

always @(posedge CK) begin
if( RST == 1 ) begin
	PC <= 0;
	STAGE <= 0;
	RW<=1;
end else if( STAGE == 0 ) begin
	RW <= 1;
	INST <= ID;
	STAGE <= 1;
end else if( STAGE == 1 ) begin
	if( (OPCODE[3:0] == 'b 1000) || (OPCODE[3:0] == 'b 1001 && FLAG == 1 ) ) PCI <= BBUS;
	else PCI <= PCn;
	if( OPCODE[3] == 0 ) begin
      FUA <= ABUS;
      FUB <= BBUS;
	end else if( OPCODE[2:1] == 'b 01) begin
		RW <= OPCODE[0];
		LSUA <= ABUS;
		LSUB <= BBUS;
	end
	STAGE <= 2;
end else if( STAGE == 2 ) begin
	if( OPCODE[3] == 0 ) begin
		case(OPCODE[2:0])
         'b 000: FUC<=FUA+FUB;
			'b 001: FUC<=FUA-FUB;
			'b 010: FUC<=FUA>>FUB;
			'b 011: FUC<=FUA<<FUB;
			'b 100: FUC<=FUA|FUB;
         'b 101: FUC<=FUA&FUB;
			'b 110: FUC<=~FUA;
			'b 111: FUC<=FUA^FUB;
		endcase
	end else if( OPCODE[3:1] == 'b 101 ) begin
		if( OPCODE[0] == 1 ) begin
         RW <= 1;
         LSUC <= DD;
		end else begin
         RW <= 0;
      end
      end else if( OPCODE[3:0] == 'b 1000 ) PCC <= PCn;
	STAGE <= 3;
end else if( STAGE == 3 ) begin
	RW <= 1;
	if( OPCODE[3] == 0 ) begin
		if( CBUS == 0 ) FLAG <= 1;
      else FLAG <= 0;
	end
   RF[OPR1] <= CBUS;
   PC <= PCI;
	STAGE <= 0;
end
end
endmodule

HWDesign2016/0527/simcpu4.v
module simcpu;
reg CK, RST;
wire RW;
wire [15:0] IA, DA, DD;
reg [15:0] ID, DDi;
reg [15:0] IMEM [0:127], DMEM[0:127];

	CPU c(CK,RST,IA,ID,DA,DD,RW);

   assign DD = ((RW == 1) ? DDi : 'b Z);

initial begin
	$dumpfile("cpu.vcd");
	$dumpvars;
	CK = 0;
	RST = 0;
#5	RST = 1;
#100	RST = 0;

        #10000 $finish;
end

always @(negedge CK) begin
	ID = IMEM[IA];
end

always @(negedge CK) begin
   if( RW == 1 ) DDi = DMEM[DA];
   else DMEM[DA] = DD;
end

initial begin
	DMEM[0] = 3;
	DMEM[1] = 4;
   IMEM[0]=	'b 1100_0001_0000_0000;
   IMEM[1]=	'b 1100_0010_0000_0001;
   IMEM[2]=	'b 1011_0011_0000_0001;
   IMEM[3]=	'b 1011_0100_0000_0010;
   IMEM[4]=	'b 1100_0101_0000_0000;
   IMEM[5]=	'b 0000_0101_0101_0011;
   IMEM[6]=	'b 0001_0100_0100_0010;
	IMEM[7]=	'b 1100_0111_0000_1011;
	IMEM[8]=	'b 1001_0000_0000_0111;
	IMEM[9]=	'b 1100_0110_0000_0101;
	IMEM[10]=	'b 1000_0000_0000_0110;
	IMEM[11]=	'b 1100_1000_0000_0010;
	IMEM[12]=	'b 1010_0000_0101_1000;
end

always #10 CK = ~CK;

endmodule

HWDesign2016/0527/cpu.vcd
$date
	Fri Jun  3 11:14:05 2016
$end
$version
	Icarus Verilog
$end
$timescale
	1s
$end
$scope module simcpu $end
$var wire 16 ! DA [15:0] $end
$var wire 16 " DD [15:0] $end
$var wire 16 # IA [15:0] $end
$var wire 1 $ RW $end
$var reg 1 % CK $end
$var reg 16 & DDi [15:0] $end
$var reg 16 ' ID [15:0] $end
$var reg 1 ( RST $end
$scope module c $end
$var wire 16 ) ABUS [15:0] $end
$var wire 16 * BBUS [15:0] $end
$var wire 16 + CBUS [15:0] $end
$var wire 1 , CK $end
$var wire 16 - DA [15:0] $end
$var wire 16 . DD [15:0] $end
$var wire 16 / IA [15:0] $end
$var wire 16 0 ID [15:0] $end
$var wire 8 1 IMM [7:0] $end
$var wire 4 2 OPCODE [3:0] $end
$var wire 4 3 OPR1 [3:0] $end
$var wire 4 4 OPR2 [3:0] $end
$var wire 4 5 OPR3 [3:0] $end
$var wire 16 6 PCn [15:0] $end
$var wire 1 7 RST $end
$var reg 1 8 FLAG $end
$var reg 16 9 FUA [15:0] $end
$var reg 16 : FUB [15:0] $end
$var reg 16 ; FUC [15:0] $end
$var reg 16 < INST [15:0] $end
$var reg 16 = LSUA [15:0] $end
$var reg 16 > LSUB [15:0] $end
$var reg 16 ? LSUC [15:0] $end
$var reg 16 @ PC [15:0] $end
$var reg 16 A PCC [15:0] $end
$var reg 16 B PCI [15:0] $end
$var reg 1 C RW $end
$var reg 2 D STAGE [1:0] $end
$upscope $end
$upscope $end
$enddefinitions $end
#0
$dumpvars
bx D
xC
bx B
bx A
bx @
bx ?
bx >
bx =
bx <
bx ;
bx :
bx 9
x8
07
bx 6
bx 5
bx 4
bx 3
bx 2
bx 1
bx 0
bx /
bx .
bx -
0,
bx +
bx *
bx )
0(
bx '
bx &
0%
x$
bx #
bx "
bx !
$end
#5
1(
17
#10
b1 6
1C
1$
b0 D
b0 @
b0 #
b0 /
1%
1,
#20
b1100000100000000 '
b1100000100000000 0
0%
0,
#30
1%
1,
#40
0%
0,
#50
1%
1,
#60
0%
0,
#70
1%
1,
#80
0%
0,
#90
1%
1,
#100
0%
0,
#105
0(
07
#110
b0 +
b0 )
b0 *
b1100 2
b1 3
b0 4
b0 5
b0 1
b1 D
b1100000100000000 <
1%
1,
#120
0%
0,
#130
b10 D
b1 B
1%
1,
#140
0%
0,
#150
b11 D
1%
1,
#160
0%
0,
#170
b10 6
b0 D
b1 @
b1 #
b1 /
1%
1,
#180
b1100001000000001 '
b1100001000000001 0
0%
0,
#190
b1 +
b10 3
b1 5
b1 1
b1 D
b1100001000000001 <
1%
1,
#200
0%
0,
#210
b10 D
b10 B
1%
1,
#220
0%
0,
#230
b11 D
1%
1,
#240
0%
0,
#250
b11 6
b0 D
b10 @
b10 #
b10 /
1%
1,
#260
b1011001100000001 '
b1011001100000001 0
0%
0,
#270
bx +
b1011 2
b11 3
b1 D
b1011001100000001 <
1%
1,
#280
0%
0,
#290
b10 D
b0 >
b0 !
b0 -
b0 =
b11 B
1%
1,
#300
b11 "
b11 .
b11 &
0%
0,
#310
b11 +
b11 D
b11 ?
1%
1,
#320
0%
0,
#330
b100 6
b0 D
b11 @
b11 #
b11 /
1%
1,
#340
b1011010000000010 '
b1011010000000010 0
0%
0,
#350
b1 *
b100 3
b10 5
b10 1
b1 D
b1011010000000010 <
1%
1,
#360
0%
0,
#370
b10 D
b1 >
b1 !
b1 -
b100 B
1%
1,
#380
b100 "
b100 .
b100 &
0%
0,
#390
b100 +
b11 D
b100 ?
1%
1,
#400
0%
0,
#410
b101 6
b0 D
b100 @
b100 #
b100 /
1%
1,
#420
b1100010100000000 '
b1100010100000000 0
0%
0,
#430
b0 +
b0 *
b1100 2
b101 3
b0 5
b0 1
b1 D
b1100010100000000 <
1%
1,
#440
0%
0,
#450
b10 D
b101 B
1%
1,
#460
0%
0,
#470
b11 D
1%
1,
#480
0%
0,
#490
b110 6
b0 D
b101 @
b101 #
b101 /
1%
1,
#500
b10101010011 '
b10101010011 0
0%
0,
#510
bx +
b11 *
b0 2
b101 4
b11 5
b1010011 1
b1 D
b10101010011 <
1%
1,
#520
0%
0,
#530
b10 D
b11 :
b0 9
b110 B
1%
1,
#540
0%
0,
#550
b11 +
b11 D
b11 ;
1%
1,
#560
0%
0,
#570
b111 6
b11 )
b0 D
b110 @
b110 #
b110 /
08
1%
1,
#580
b1010001000010 '
b1010001000010 0
0%
0,
#590
b100 )
b1 *
b1 2
b100 3
b100 4
b10 5
b1000010 1
b1 D
b1010001000010 <
1%
1,
#600
0%
0,
#610
b10 D
b1 :
b100 9
b111 B
1%
1,
#620
0%
0,
#630
b11 D
1%
1,
#640
0%
0,
#650
b1000 6
b11 )
b0 D
b111 @
b111 #
b111 /
1%
1,
#660
b1100011100001011 '
b1100011100001011 0
0%
0,
#670
b1011 +
b0 )
bx *
b1100 2
b111 3
b0 4
b1011 5
b1011 1
b1 D
b1100011100001011 <
1%
1,
#680
0%
0,
#690
b10 D
b1000 B
1%
1,
#700
0%
0,
#710
b11 D
1%
1,
#720
0%
0,
#730
b1001 6
b0 D
b1000 @
b1000 #
b1000 /
1%
1,
#740
b1001000000000111 '
b1001000000000111 0
0%
0,
#750
bz +
b1011 *
b1001 2
b0 3
b111 5
b111 1
b1 D
b1001000000000111 <
1%
1,
#760
0%
0,
#770
b10 D
b1001 B
1%
1,
#780
0%
0,
#790
b11 D
1%
1,
#800
0%
0,
#810
b1010 6
b0 D
b1001 @
b1001 #
b1001 /
1%
1,
#820
b1100011000000101 '
b1100011000000101 0
0%
0,
#830
b101 +
b11 *
b1100 2
b110 3
b101 5
b101 1
b1 D
b1100011000000101 <
1%
1,
#840
0%
0,
#850
b10 D
b1010 B
1%
1,
#860
0%
0,
#870
b11 D
1%
1,
#880
0%
0,
#890
b1011 6
b0 D
b1010 @
b1010 #
b1010 /
1%
1,
#900
b1000000000000110 '
b1000000000000110 0
0%
0,
#910
bx +
b101 *
b1000 2
b0 3
b110 5
b110 1
b1 D
b1000000000000110 <
1%
1,
#920
0%
0,
#930
b10 D
b101 B
1%
1,
#940
0%
0,
#950
b1011 +
b11 D
b1011 A
1%
1,
#960
0%
0,
#970
b110 6
b0 D
b101 @
b101 #
b101 /
1%
1,
#980
b10101010011 '
b10101010011 0
0%
0,
#990
b11 +
b11 )
b11 *
b0 2
b101 3
b101 4
b11 5
b1010011 1
b1 D
b10101010011 <
1%
1,
#1000
0%
0,
#1010
b10 D
b11 :
b11 9
b110 B
1%
1,
#1020
0%
0,
#1030
b110 +
b11 D
b110 ;
1%
1,
#1040
0%
0,
#1050
b111 6
b110 )
b0 D
b110 @
b110 #
b110 /
1%
1,
#1060
b1010001000010 '
b1010001000010 0
0%
0,
#1070
b11 )
b1 *
b1 2
b100 3
b100 4
b10 5
b1000010 1
b1 D
b1010001000010 <
1%
1,
#1080
0%
0,
#1090
b10 D
b1 :
b111 B
1%
1,
#1100
0%
0,
#1110
b10 +
b11 D
b10 ;
1%
1,
#1120
0%
0,
#1130
b1000 6
b10 )
b0 D
b111 @
b111 #
b111 /
1%
1,
#1140
b1100011100001011 '
b1100011100001011 0
0%
0,
#1150
b1011 +
b0 )
bx *
b1100 2
b111 3
b0 4
b1011 5
b1011 1
b1 D
b1100011100001011 <
1%
1,
#1160
0%
0,
#1170
b10 D
b1000 B
1%
1,
#1180
0%
0,
#1190
b11 D
1%
1,
#1200
0%
0,
#1210
b1001 6
b0 D
b1000 @
b1000 #
b1000 /
1%
1,
#1220
b1001000000000111 '
b1001000000000111 0
0%
0,
#1230
bz +
b1011 *
b1001 2
b0 3
b111 5
b111 1
b1 D
b1001000000000111 <
1%
1,
#1240
0%
0,
#1250
b10 D
b1001 B
1%
1,
#1260
0%
0,
#1270
b11 D
1%
1,
#1280
0%
0,
#1290
b1010 6
b0 D
b1001 @
b1001 #
b1001 /
1%
1,
#1300
b1100011000000101 '
b1100011000000101 0
0%
0,
#1310
b101 +
b110 *
b1100 2
b110 3
b101 5
b101 1
b1 D
b1100011000000101 <
1%
1,
#1320
0%
0,
#1330
b10 D
b1010 B
1%
1,
#1340
0%
0,
#1350
b11 D
1%
1,
#1360
0%
0,
#1370
b1011 6
b0 D
b1010 @
b1010 #
b1010 /
1%
1,
#1380
b1000000000000110 '
b1000000000000110 0
0%
0,
#1390
b1011 +
b101 *
b1000 2
b0 3
b110 5
b110 1
b1 D
b1000000000000110 <
1%
1,
#1400
0%
0,
#1410
b10 D
b101 B
1%
1,
#1420
0%
0,
#1430
b11 D
1%
1,
#1440
0%
0,
#1450
b110 6
b0 D
b101 @
b101 #
b101 /
1%
1,
#1460
b10101010011 '
b10101010011 0
0%
0,
#1470
b10 +
b110 )
b11 *
b0 2
b101 3
b101 4
b11 5
b1010011 1
b1 D
b10101010011 <
1%
1,
#1480
0%
0,
#1490
b10 D
b11 :
b110 9
b110 B
1%
1,
#1500
0%
0,
#1510
b1001 +
b11 D
b1001 ;
1%
1,
#1520
0%
0,
#1530
b111 6
b1001 )
b0 D
b110 @
b110 #
b110 /
1%
1,
#1540
b1010001000010 '
b1010001000010 0
0%
0,
#1550
b10 )
b1 *
b1 2
b100 3
b100 4
b10 5
b1000010 1
b1 D
b1010001000010 <
1%
1,
#1560
0%
0,
#1570
b10 D
b1 :
b10 9
b111 B
1%
1,
#1580
0%
0,
#1590
b1 +
b11 D
b1 ;
1%
1,
#1600
0%
0,
#1610
b1000 6
b1 )
b0 D
b111 @
b111 #
b111 /
1%
1,
#1620
b1100011100001011 '
b1100011100001011 0
0%
0,
#1630
b1011 +
b0 )
bx *
b1100 2
b111 3
b0 4
b1011 5
b1011 1
b1 D
b1100011100001011 <
1%
1,
#1640
0%
0,
#1650
b10 D
b1000 B
1%
1,
#1660
0%
0,
#1670
b11 D
1%
1,
#1680
0%
0,
#1690
b1001 6
b0 D
b1000 @
b1000 #
b1000 /
1%
1,
#1700
b1001000000000111 '
b1001000000000111 0
0%
0,
#1710
bz +
b1011 *
b1001 2
b0 3
b111 5
b111 1
b1 D
b1001000000000111 <
1%
1,
#1720
0%
0,
#1730
b10 D
b1001 B
1%
1,
#1740
0%
0,
#1750
b11 D
1%
1,
#1760
0%
0,
#1770
b1010 6
b0 D
b1001 @
b1001 #
b1001 /
1%
1,
#1780
b1100011000000101 '
b1100011000000101 0
0%
0,
#1790
b101 +
b1001 *
b1100 2
b110 3
b101 5
b101 1
b1 D
b1100011000000101 <
1%
1,
#1800
0%
0,
#1810
b10 D
b1010 B
1%
1,
#1820
0%
0,
#1830
b11 D
1%
1,
#1840
0%
0,
#1850
b1011 6
b0 D
b1010 @
b1010 #
b1010 /
1%
1,
#1860
b1000000000000110 '
b1000000000000110 0
0%
0,
#1870
b1011 +
b101 *
b1000 2
b0 3
b110 5
b110 1
b1 D
b1000000000000110 <
1%
1,
#1880
0%
0,
#1890
b10 D
b101 B
1%
1,
#1900
0%
0,
#1910
b11 D
1%
1,
#1920
0%
0,
#1930
b110 6
b0 D
b101 @
b101 #
b101 /
1%
1,
#1940
b10101010011 '
b10101010011 0
0%
0,
#1950
b1 +
b1001 )
b11 *
b0 2
b101 3
b101 4
b11 5
b1010011 1
b1 D
b10101010011 <
1%
1,
#1960
0%
0,
#1970
b10 D
b11 :
b1001 9
b110 B
1%
1,
#1980
0%
0,
#1990
b1100 +
b11 D
b1100 ;
1%
1,
#2000
0%
0,
#2010
b111 6
b1100 )
b0 D
b110 @
b110 #
b110 /
1%
1,
#2020
b1010001000010 '
b1010001000010 0
0%
0,
#2030
b1 )
b1 *
b1 2
b100 3
b100 4
b10 5
b1000010 1
b1 D
b1010001000010 <
1%
1,
#2040
0%
0,
#2050
b10 D
b1 :
b1 9
b111 B
1%
1,
#2060
0%
0,
#2070
b0 +
b11 D
b0 ;
1%
1,
#2080
0%
0,
#2090
b1000 6
b0 )
b0 D
b111 @
b111 #
b111 /
18
1%
1,
#2100
b1100011100001011 '
b1100011100001011 0
0%
0,
#2110
b1011 +
bx *
b1100 2
b111 3
b0 4
b1011 5
b1011 1
b1 D
b1100011100001011 <
1%
1,
#2120
0%
0,
#2130
b10 D
b1000 B
1%
1,
#2140
0%
0,
#2150
b11 D
1%
1,
#2160
0%
0,
#2170
b1001 6
b0 D
b1000 @
b1000 #
b1000 /
1%
1,
#2180
b1001000000000111 '
b1001000000000111 0
0%
0,
#2190
bz +
b1011 *
b1001 2
b0 3
b111 5
b111 1
b1 D
b1001000000000111 <
1%
1,
#2200
0%
0,
#2210
b10 D
b1011 B
1%
1,
#2220
0%
0,
#2230
b11 D
1%
1,
#2240
0%
0,
#2250
b1100 6
b0 D
b1011 @
b1011 #
b1011 /
1%
1,
#2260
b1100100000000010 '
b1100100000000010 0
0%
0,
#2270
b10 +
b1 *
b1100 2
b1000 3
b10 5
b10 1
b1 D
b1100100000000010 <
1%
1,
#2280
0%
0,
#2290
b10 D
b1100 B
1%
1,
#2300
0%
0,
#2310
b11 D
1%
1,
#2320
0%
0,
#2330
b1101 6
b0 D
b1100 @
b1100 #
b1100 /
1%
1,
#2340
b1010000001011000 '
b1010000001011000 0
0%
0,
#2350
b100 +
b1100 )
b10 *
b1010 2
b0 3
b101 4
b1000 5
b1011000 1
b1 D
b1010000001011000 <
1%
1,
#2360
0%
0,
#2370
b1100 "
b1100 .
b10 D
b10 >
b10 !
b10 -
b1100 =
0C
0$
b1101 B
1%
1,
#2380
0%
0,
#2390
b11 D
1%
1,
#2400
0%
0,
#2410
b1110 6
b100 "
b100 .
b0 D
b1101 @
b1101 #
b1101 /
1C
1$
1%
1,
#2420
b1100 "
b1100 .
bx '
bx 0
b1100 &
0%
0,
#2430
bx +
bx )
bx *
bx 2
bx 3
bx 4
bx 5
bx 1
b1 D
bx <
1%
1,
#2440
0%
0,
#2450
b10 D
b1110 B
1%
1,
#2460
0%
0,
#2470
b11 D
1%
1,
#2480
0%
0,
#2490
b1111 6
b0 D
b1110 @
b1110 #
b1110 /
1%
1,
#2500
0%
0,
#2510
b1 D
1%
1,
#2520
0%
0,
#2530
b10 D
b1111 B
1%
1,
#2540
0%
0,
#2550
b11 D
1%
1,
#2560
0%
0,
#2570
b10000 6
b0 D
b1111 @
b1111 #
b1111 /
1%
1,
#2580
0%
0,
#2590
b1 D
1%
1,
#2600
0%
0,
#2610
b10 D
b10000 B
1%
1,
#2620
0%
0,
#2630
b11 D
1%
1,
#2640
0%
0,
#2650
b10001 6
b0 D
b10000 @
b10000 #
b10000 /
1%
1,
#2660
0%
0,
#2670
b1 D
1%
1,
#2680
0%
0,
#2690
b10 D
b10001 B
1%
1,
#2700
0%
0,
#2710
b11 D
1%
1,
#2720
0%
0,
#2730
b10010 6
b0 D
b10001 @
b10001 #
b10001 /
1%
1,
#2740
0%
0,
#2750
b1 D
1%
1,
#2760
0%
0,
#2770
b10 D
b10010 B
1%
1,
#2780
0%
0,
#2790
b11 D
1%
1,
#2800
0%
0,
#2810
b10011 6
b0 D
b10010 @
b10010 #
b10010 /
1%
1,
#2820
0%
0,
#2830
b1 D
1%
1,
#2840
0%
0,
#2850
b10 D
b10011 B
1%
1,
#2860
0%
0,
#2870
b11 D
1%
1,
#2880
0%
0,
#2890
b10100 6
b0 D
b10011 @
b10011 #
b10011 /
1%
1,
#2900
0%
0,
#2910
b1 D
1%
1,
#2920
0%
0,
#2930
b10 D
b10100 B
1%
1,
#2940
0%
0,
#2950
b11 D
1%
1,
#2960
0%
0,
#2970
b10101 6
b0 D
b10100 @
b10100 #
b10100 /
1%
1,
#2980
0%
0,
#2990
b1 D
1%
1,
#3000
0%
0,
#3010
b10 D
b10101 B
1%
1,
#3020
0%
0,
#3030
b11 D
1%
1,
#3040
0%
0,
#3050
b10110 6
b0 D
b10101 @
b10101 #
b10101 /
1%
1,
#3060
0%
0,
#3070
b1 D
1%
1,
#3080
0%
0,
#3090
b10 D
b10110 B
1%
1,
#3100
0%
0,
#3110
b11 D
1%
1,
#3120
0%
0,
#3130
b10111 6
b0 D
b10110 @
b10110 #
b10110 /
1%
1,
#3140
0%
0,
#3150
b1 D
1%
1,
#3160
0%
0,
#3170
b10 D
b10111 B
1%
1,
#3180
0%
0,
#3190
b11 D
1%
1,
#3200
0%
0,
#3210
b11000 6
b0 D
b10111 @
b10111 #
b10111 /
1%
1,
#3220
0%
0,
#3230
b1 D
1%
1,
#3240
0%
0,
#3250
b10 D
b11000 B
1%
1,
#3260
0%
0,
#3270
b11 D
1%
1,
#3280
0%
0,
#3290
b11001 6
b0 D
b11000 @
b11000 #
b11000 /
1%
1,
#3300
0%
0,
#3310
b1 D
1%
1,
#3320
0%
0,
#3330
b10 D
b11001 B
1%
1,
#3340
0%
0,
#3350
b11 D
1%
1,
#3360
0%
0,
#3370
b11010 6
b0 D
b11001 @
b11001 #
b11001 /
1%
1,
#3380
0%
0,
#3390
b1 D
1%
1,
#3400
0%
0,
#3410
b10 D
b11010 B
1%
1,
#3420
0%
0,
#3430
b11 D
1%
1,
#3440
0%
0,
#3450
b11011 6
b0 D
b11010 @
b11010 #
b11010 /
1%
1,
#3460
0%
0,
#3470
b1 D
1%
1,
#3480
0%
0,
#3490
b10 D
b11011 B
1%
1,
#3500
0%
0,
#3510
b11 D
1%
1,
#3520
0%
0,
#3530
b11100 6
b0 D
b11011 @
b11011 #
b11011 /
1%
1,
#3540
0%
0,
#3550
b1 D
1%
1,
#3560
0%
0,
#3570
b10 D
b11100 B
1%
1,
#3580
0%
0,
#3590
b11 D
1%
1,
#3600
0%
0,
#3610
b11101 6
b0 D
b11100 @
b11100 #
b11100 /
1%
1,
#3620
0%
0,
#3630
b1 D
1%
1,
#3640
0%
0,
#3650
b10 D
b11101 B
1%
1,
#3660
0%
0,
#3670
b11 D
1%
1,
#3680
0%
0,
#3690
b11110 6
b0 D
b11101 @
b11101 #
b11101 /
1%
1,
#3700
0%
0,
#3710
b1 D
1%
1,
#3720
0%
0,
#3730
b10 D
b11110 B
1%
1,
#3740
0%
0,
#3750
b11 D
1%
1,
#3760
0%
0,
#3770
b11111 6
b0 D
b11110 @
b11110 #
b11110 /
1%
1,
#3780
0%
0,
#3790
b1 D
1%
1,
#3800
0%
0,
#3810
b10 D
b11111 B
1%
1,
#3820
0%
0,
#3830
b11 D
1%
1,
#3840
0%
0,
#3850
b100000 6
b0 D
b11111 @
b11111 #
b11111 /
1%
1,
#3860
0%
0,
#3870
b1 D
1%
1,
#3880
0%
0,
#3890
b10 D
b100000 B
1%
1,
#3900
0%
0,
#3910
b11 D
1%
1,
#3920
0%
0,
#3930
b100001 6
b0 D
b100000 @
b100000 #
b100000 /
1%
1,
#3940
0%
0,
#3950
b1 D
1%
1,
#3960
0%
0,
#3970
b10 D
b100001 B
1%
1,
#3980
0%
0,
#3990
b11 D
1%
1,
#4000
0%
0,
#4010
b100010 6
b0 D
b100001 @
b100001 #
b100001 /
1%
1,
#4020
0%
0,
#4030
b1 D
1%
1,
#4040
0%
0,
#4050
b10 D
b100010 B
1%
1,
#4060
0%
0,
#4070
b11 D
1%
1,
#4080
0%
0,
#4090
b100011 6
b0 D
b100010 @
b100010 #
b100010 /
1%
1,
#4100
0%
0,
#4110
b1 D
1%
1,
#4120
0%
0,
#4130
b10 D
b100011 B
1%
1,
#4140
0%
0,
#4150
b11 D
1%
1,
#4160
0%
0,
#4170
b100100 6
b0 D
b100011 @
b100011 #
b100011 /
1%
1,
#4180
0%
0,
#4190
b1 D
1%
1,
#4200
0%
0,
#4210
b10 D
b100100 B
1%
1,
#4220
0%
0,
#4230
b11 D
1%
1,
#4240
0%
0,
#4250
b100101 6
b0 D
b100100 @
b100100 #
b100100 /
1%
1,
#4260
0%
0,
#4270
b1 D
1%
1,
#4280
0%
0,
#4290
b10 D
b100101 B
1%
1,
#4300
0%
0,
#4310
b11 D
1%
1,
#4320
0%
0,
#4330
b100110 6
b0 D
b100101 @
b100101 #
b100101 /
1%
1,
#4340
0%
0,
#4350
b1 D
1%
1,
#4360
0%
0,
#4370
b10 D
b100110 B
1%
1,
#4380
0%
0,
#4390
b11 D
1%
1,
#4400
0%
0,
#4410
b100111 6
b0 D
b100110 @
b100110 #
b100110 /
1%
1,
#4420
0%
0,
#4430
b1 D
1%
1,
#4440
0%
0,
#4450
b10 D
b100111 B
1%
1,
#4460
0%
0,
#4470
b11 D
1%
1,
#4480
0%
0,
#4490
b101000 6
b0 D
b100111 @
b100111 #
b100111 /
1%
1,
#4500
0%
0,
#4510
b1 D
1%
1,
#4520
0%
0,
#4530
b10 D
b101000 B
1%
1,
#4540
0%
0,
#4550
b11 D
1%
1,
#4560
0%
0,
#4570
b101001 6
b0 D
b101000 @
b101000 #
b101000 /
1%
1,
#4580
0%
0,
#4590
b1 D
1%
1,
#4600
0%
0,
#4610
b10 D
b101001 B
1%
1,
#4620
0%
0,
#4630
b11 D
1%
1,
#4640
0%
0,
#4650
b101010 6
b0 D
b101001 @
b101001 #
b101001 /
1%
1,
#4660
0%
0,
#4670
b1 D
1%
1,
#4680
0%
0,
#4690
b10 D
b101010 B
1%
1,
#4700
0%
0,
#4710
b11 D
1%
1,
#4720
0%
0,
#4730
b101011 6
b0 D
b101010 @
b101010 #
b101010 /
1%
1,
#4740
0%
0,
#4750
b1 D
1%
1,
#4760
0%
0,
#4770
b10 D
b101011 B
1%
1,
#4780
0%
0,
#4790
b11 D
1%
1,
#4800
0%
0,
#4810
b101100 6
b0 D
b101011 @
b101011 #
b101011 /
1%
1,
#4820
0%
0,
#4830
b1 D
1%
1,
#4840
0%
0,
#4850
b10 D
b101100 B
1%
1,
#4860
0%
0,
#4870
b11 D
1%
1,
#4880
0%
0,
#4890
b101101 6
b0 D
b101100 @
b101100 #
b101100 /
1%
1,
#4900
0%
0,
#4910
b1 D
1%
1,
#4920
0%
0,
#4930
b10 D
b101101 B
1%
1,
#4940
0%
0,
#4950
b11 D
1%
1,
#4960
0%
0,
#4970
b101110 6
b0 D
b101101 @
b101101 #
b101101 /
1%
1,
#4980
0%
0,
#4990
b1 D
1%
1,
#5000
0%
0,
#5010
b10 D
b101110 B
1%
1,
#5020
0%
0,
#5030
b11 D
1%
1,
#5040
0%
0,
#5050
b101111 6
b0 D
b101110 @
b101110 #
b101110 /
1%
1,
#5060
0%
0,
#5070
b1 D
1%
1,
#5080
0%
0,
#5090
b10 D
b101111 B
1%
1,
#5100
0%
0,
#5110
b11 D
1%
1,
#5120
0%
0,
#5130
b110000 6
b0 D
b101111 @
b101111 #
b101111 /
1%
1,
#5140
0%
0,
#5150
b1 D
1%
1,
#5160
0%
0,
#5170
b10 D
b110000 B
1%
1,
#5180
0%
0,
#5190
b11 D
1%
1,
#5200
0%
0,
#5210
b110001 6
b0 D
b110000 @
b110000 #
b110000 /
1%
1,
#5220
0%
0,
#5230
b1 D
1%
1,
#5240
0%
0,
#5250
b10 D
b110001 B
1%
1,
#5260
0%
0,
#5270
b11 D
1%
1,
#5280
0%
0,
#5290
b110010 6
b0 D
b110001 @
b110001 #
b110001 /
1%
1,
#5300
0%
0,
#5310
b1 D
1%
1,
#5320
0%
0,
#5330
b10 D
b110010 B
1%
1,
#5340
0%
0,
#5350
b11 D
1%
1,
#5360
0%
0,
#5370
b110011 6
b0 D
b110010 @
b110010 #
b110010 /
1%
1,
#5380
0%
0,
#5390
b1 D
1%
1,
#5400
0%
0,
#5410
b10 D
b110011 B
1%
1,
#5420
0%
0,
#5430
b11 D
1%
1,
#5440
0%
0,
#5450
b110100 6
b0 D
b110011 @
b110011 #
b110011 /
1%
1,
#5460
0%
0,
#5470
b1 D
1%
1,
#5480
0%
0,
#5490
b10 D
b110100 B
1%
1,
#5500
0%
0,
#5510
b11 D
1%
1,
#5520
0%
0,
#5530
b110101 6
b0 D
b110100 @
b110100 #
b110100 /
1%
1,
#5540
0%
0,
#5550
b1 D
1%
1,
#5560
0%
0,
#5570
b10 D
b110101 B
1%
1,
#5580
0%
0,
#5590
b11 D
1%
1,
#5600
0%
0,
#5610
b110110 6
b0 D
b110101 @
b110101 #
b110101 /
1%
1,
#5620
0%
0,
#5630
b1 D
1%
1,
#5640
0%
0,
#5650
b10 D
b110110 B
1%
1,
#5660
0%
0,
#5670
b11 D
1%
1,
#5680
0%
0,
#5690
b110111 6
b0 D
b110110 @
b110110 #
b110110 /
1%
1,
#5700
0%
0,
#5710
b1 D
1%
1,
#5720
0%
0,
#5730
b10 D
b110111 B
1%
1,
#5740
0%
0,
#5750
b11 D
1%
1,
#5760
0%
0,
#5770
b111000 6
b0 D
b110111 @
b110111 #
b110111 /
1%
1,
#5780
0%
0,
#5790
b1 D
1%
1,
#5800
0%
0,
#5810
b10 D
b111000 B
1%
1,
#5820
0%
0,
#5830
b11 D
1%
1,
#5840
0%
0,
#5850
b111001 6
b0 D
b111000 @
b111000 #
b111000 /
1%
1,
#5860
0%
0,
#5870
b1 D
1%
1,
#5880
0%
0,
#5890
b10 D
b111001 B
1%
1,
#5900
0%
0,
#5910
b11 D
1%
1,
#5920
0%
0,
#5930
b111010 6
b0 D
b111001 @
b111001 #
b111001 /
1%
1,
#5940
0%
0,
#5950
b1 D
1%
1,
#5960
0%
0,
#5970
b10 D
b111010 B
1%
1,
#5980
0%
0,
#5990
b11 D
1%
1,
#6000
0%
0,
#6010
b111011 6
b0 D
b111010 @
b111010 #
b111010 /
1%
1,
#6020
0%
0,
#6030
b1 D
1%
1,
#6040
0%
0,
#6050
b10 D
b111011 B
1%
1,
#6060
0%
0,
#6070
b11 D
1%
1,
#6080
0%
0,
#6090
b111100 6
b0 D
b111011 @
b111011 #
b111011 /
1%
1,
#6100
0%
0,
