HWDesign2016/0422/stm.v
module stm(ck,rst,x);
input	ck, rst;
output	[3:0] x;
reg [3:0] x;
reg	st;
always @(posedge ck) begin
	if( rst == 1 ) begin
		st <= 0;
		x <= 0;
	end else begin
		if( st == 0 ) begin
			if( x == 0 ) st <= 1;
			else x <= x-1;
		end else begin
			if( x == 15 ) st <= 0;
			else x <= x+1;
		end
	end
end
endmodule

HWDesign2016/0422/simstm.v
module simstm;
reg ck, rst;
wire [3:0] x;
initial begin
	$dumpvars;
	$dumpfile("stm.vcd");
	$monitor( "ck = %b, st = %b: x = %x", s.ck, s.st, s.x );
	ck=0; rst=0;
	#20 rst=1;
	#60 rst=0;
	#800
	  if( x == 7 )  $display("OK\n");
   $finish;
end
always #10	ck<=~ck;

stm	s(ck,rst,x);

endmodule

HWDesign2016/0422/dump.vcd
$date
	Fri Apr 22 11:46:48 2016
$end
$version
	Icarus Verilog
$end
$timescale
	1s
$end
$scope module simstm $end
$var wire 4 ! x [3:0] $end
$var reg 1 " ck $end
$var reg 1 # rst $end
$scope module s $end
$var wire 1 $ ck $end
$var wire 1 % rst $end
$var reg 1 & st $end
$var reg 4 ' x [3:0] $end
$upscope $end
$upscope $end
$enddefinitions $end
#0
$dumpvars
bx '
x&
0%
0$
0#
0"
bx !
$end
#10
1"
1$
#20
0"
0$
1#
1%
#30
b0 '
b0 !
0&
1"
1$
#40
0"
0$
#50
1"
1$
#60
0"
0$
#70
1"
1$
#80
0"
0$
0#
0%
#90
1&
1"
1$
#100
0"
0$
#110
b1 '
b1 !
1"
1$
#120
0"
0$
#130
b10 '
b10 !
1"
1$
#140
0"
0$
#150
b11 '
b11 !
1"
1$
#160
0"
0$
#170
b100 '
b100 !
1"
1$
#180
0"
0$
#190
b101 '
b101 !
1"
1$
#200
0"
0$
#210
b110 '
b110 !
1"
1$
#220
0"
0$
#230
b111 '
b111 !
1"
1$
#240
0"
0$
#250
b1000 '
b1000 !
1"
1$
#260
0"
0$
#270
b1001 '
b1001 !
1"
1$
#280
0"
0$
#290
b1010 '
b1010 !
1"
1$
#300
0"
0$
#310
b1011 '
b1011 !
1"
1$
#320
0"
0$
#330
b1100 '
b1100 !
1"
1$
#340
0"
0$
#350
b1101 '
b1101 !
1"
1$
#360
0"
0$
#370
b1110 '
b1110 !
1"
1$
#380
0"
0$
#390
b1111 '
b1111 !
1"
1$
#400
0"
0$
#410
0&
1"
1$
#420
0"
0$
#430
b1110 '
b1110 !
1"
1$
#440
0"
0$
#450
b1101 '
b1101 !
1"
1$
#460
0"
0$
#470
b1100 '
b1100 !
1"
1$
#480
0"
0$
#490
b1011 '
b1011 !
1"
1$
#500
0"
0$
#510
b1010 '
b1010 !
1"
1$
#520
0"
0$
#530
b1001 '
b1001 !
1"
1$
#540
0"
0$
#550
b1000 '
b1000 !
1"
1$
#560
0"
0$
#570
b111 '
b111 !
1"
1$
#580
0"
0$
#590
b110 '
b110 !
1"
1$
#600
0"
0$
#610
b101 '
b101 !
1"
1$
#620
0"
0$
#630
b100 '
b100 !
1"
1$
#640
0"
0$
#650
b11 '
b11 !
1"
1$
#660
0"
0$
#670
b10 '
b10 !
1"
1$
#680
0"
0$
#690
b1 '
b1 !
1"
1$
#700
0"
0$
#710
b0 '
b0 !
1"
1$
#720
0"
0$
#730
1&
1"
1$
#740
0"
0$
#750
b1 '
b1 !
1"
1$
#760
0"
0$
#770
b10 '
b10 !
1"
1$
#780
0"
0$
#790
b11 '
b11 !
1"
1$
#800
0"
0$
#810
b100 '
b100 !
1"
1$
#820
0"
0$
#830
b101 '
b101 !
1"
1$
#840
0"
0$
#850
b110 '
b110 !
1"
1$
#860
0"
0$
#870
b111 '
b111 !
1"
1$
